src/branch_unit.v
//=====================================================================
// File        : branch_unit.v
// Author      : Prabhat Pandey
// Created On  : 16-Feb-2026
// Project     : RV32I Single-Cycle 32-bit RISC-V Processor
// Module Name : branch_unit
// Description :
//   This module implements the branch decision logic for RV32I.
//
//   It evaluates the branch condition based on:
//     - funct3 field (branch type)
//     - rs1 and rs2 register values
//
// Supported RV32I Branch Instructions (funct3):
//   000 : BEQ   (branch if equal)
//   001 : BNE   (branch if not equal)
//   100 : BLT   (branch if rs1 < rs2, signed)
//   101 : BGE   (branch if rs1 >= rs2, signed)
//   110 : BLTU  (branch if rs1 < rs2, unsigned)
//   111 : BGEU  (branch if rs1 >= rs2, unsigned)
//
// Inputs:
//   - funct3   : instruction funct3 field
//   - rs1_val  : 32-bit value from register rs1
//   - rs2_val  : 32-bit value from register rs2
//
// Output:
//   - take_branch : 1 if branch condition is true, else 0
//
// Notes:
//   - This module only decides the condition.
//   - PC target calculation (PC + immB) is handled separately in
//     pc_next_logic.
//
// Revision History:
//   - 16-Feb-2026 : Initial version
//=====================================================================

module branch_unit (
    input  wire [2:0]  funct3,        // Branch funct3
    input  wire [31:0] rs1_val,        // rs1 register value
    input  wire [31:0] rs2_val,        // rs2 register value
    output reg         take_branch     // Branch decision output
);

    //=================================================================
    // Internal comparison signals
    //=================================================================
    wire eq;
    wire lt_signed;
    wire lt_unsigned;

    assign eq          = (rs1_val == rs2_val);
    assign lt_signed   = ($signed(rs1_val) < $signed(rs2_val));
    assign lt_unsigned = (rs1_val < rs2_val);

    //=================================================================
    // Branch decision logic (combinational)
    //=================================================================
    always @(*) begin
        take_branch = 1'b0;

        case (funct3)

            3'b000: begin
                // BEQ
                take_branch = eq;
            end

            3'b001: begin
                // BNE
                take_branch = ~eq;
            end

            3'b100: begin
                // BLT (signed)
                take_branch = lt_signed;
            end

            3'b101: begin
                // BGE (signed) => !(rs1 < rs2)
                take_branch = ~lt_signed;
            end

            3'b110: begin
                // BLTU (unsigned)
                take_branch = lt_unsigned;
            end

            3'b111: begin
                // BGEU (unsigned) => !(rs1 < rs2)
                take_branch = ~lt_unsigned;
            end

            default: begin
                // Not a valid branch funct3
                take_branch = 1'b0;
            end

        endcase
    end

endmodule

RTL_Verification/tb_branch_unit.v
//=====================================================================
// File        : tb_branch_unit.v
// Author      : Prabhat Pandey
// Created On  : 16-Feb-2026
// Project     : RV32I Single-Cycle 32-bit RISC-V Processor
// Testbench   : tb_branch_unit
// Description :
//   Fully self-checking testbench for branch_unit.v
//
// Branch funct3 encoding (RV32I):
//   000 : BEQ
//   001 : BNE
//   100 : BLT   (signed)
//   101 : BGE   (signed)
//   110 : BLTU  (unsigned)
//   111 : BGEU  (unsigned)
//
// Verification Features:
//   - Fully self-checking
//   - Input print per test
//   - Expected output print
//   - Actual output print
//   - PASS/FAIL per test
//   - Global counters
//   - Final verification summary report
//
// Run Commands:
//   iverilog -o ./Verification_Results/result_tb_branch_unit ./src/branch_unit.v ./RTL_Verification/tb_branch_unit.v
//   vvp ./Verification_Results/result_tb_branch_unit
//=====================================================================

`timescale 1ns/1ps

module tb_branch_unit;

    //=============================================================
    // Testbench Parameters
    //=============================================================
    localparam integer TEST_DELAY = 10; // ns between tests for waveform visibility

    //=============================================================
    // DUT Signals
    //=============================================================
    reg  [2:0]  funct3;
    reg  [31:0] rs1_val;
    reg  [31:0] rs2_val;
    wire        take_branch;

    //=============================================================
    // Instantiate DUT
    //=============================================================
    branch_unit dut (
        .funct3      (funct3),
        .rs1_val     (rs1_val),
        .rs2_val     (rs2_val),
        .take_branch (take_branch)
    );

    //=============================================================
    // Global Counters
    //=============================================================
    integer total_tests;
    integer passed_tests;
    integer failed_tests;

    //=============================================================
    // VCD Dump (for GTKWave)
    //=============================================================
    initial begin
        $dumpfile("Verification_Results/vcd/tb_branch_unit.vcd");
        $dumpvars(0, tb_branch_unit);
    end

    //=============================================================
    // Task: Divider
    //=============================================================
    task print_divider;
        begin
            $display("----------------------------------------------------------------");
        end
    endtask

    //=============================================================
    // Task: Run One Branch Test
    //=============================================================
    task run_test;
        input [8*70:1] test_name;
        input [2:0]    funct3_in;
        input [31:0]   rs1_in;
        input [31:0]   rs2_in;
        input          expected_take;

        reg got_take;
        begin
            total_tests = total_tests + 1;

            print_divider();
            $display("TEST : %s", test_name);

            // Apply inputs
            funct3  = funct3_in;
            rs1_val = rs1_in;
            rs2_val = rs2_in;

            #2; // combinational settle
            got_take = take_branch;

            // Print Inputs
            $display("Inputs:");
            $display("   funct3      = %03b", funct3_in);
            $display("   rs1_val     = %08h", rs1_in);
            $display("   rs2_val     = %08h", rs2_in);
            $display("   rs1 signed  = %0d", $signed(rs1_in));
            $display("   rs2 signed  = %0d", $signed(rs2_in));

            // Print Expected
            $display("");
            $display("Expected:");
            $display("   take_branch = %0d", expected_take);

            // Print Got
            $display("");
            $display("Got:");
            $display("   take_branch = %0d", got_take);

            // Compare
            if (got_take === expected_take) begin
                passed_tests = passed_tests + 1;
                $display("STATUS: PASS");
            end
            else begin
                failed_tests = failed_tests + 1;
                $display("STATUS: FAIL");
            end

            print_divider();
            $display("");

            #(TEST_DELAY);
        end
    endtask

    //=============================================================
    // Main Test Sequence
    //=============================================================
    initial begin

        // Init counters
        total_tests  = 0;
        passed_tests = 0;
        failed_tests = 0;

        // Init inputs
        funct3  = 3'b000;
        rs1_val = 32'h0000_0000;
        rs2_val = 32'h0000_0000;

        $display("====================================================");
        $display(" BRANCH_UNIT VERIFICATION STARTED — Author: Prabhat Pandey");
        $display("====================================================");
        $display("");

        //=========================================================
        // BEQ tests
        //=========================================================
        run_test("BEQ true (equal)",
                 3'b000, 32'h0000_0010, 32'h0000_0010, 1'b1);

        run_test("BEQ false (not equal)",
                 3'b000, 32'h0000_0010, 32'h0000_0011, 1'b0);

        //=========================================================
        // BNE tests
        //=========================================================
        run_test("BNE true (not equal)",
                 3'b001, 32'h0000_0010, 32'h0000_0011, 1'b1);

        run_test("BNE false (equal)",
                 3'b001, 32'hABCD_EF01, 32'hABCD_EF01, 1'b0);

        //=========================================================
        // BLT (signed) tests
        //=========================================================
        run_test("BLT signed: -5 < 5 (true)",
                 3'b100, 32'hFFFF_FFFB, 32'h0000_0005, 1'b1);

        run_test("BLT signed: 5 < -5 (false)",
                 3'b100, 32'h0000_0005, 32'hFFFF_FFFB, 1'b0);

        run_test("BLT signed: -10 < -5 (true)",
                 3'b100, 32'hFFFF_FFF6, 32'hFFFF_FFFB, 1'b1);

        //=========================================================
        // BGE (signed) tests
        //=========================================================
        run_test("BGE signed: 5 >= 5 (true)",
                 3'b101, 32'h0000_0005, 32'h0000_0005, 1'b1);

        run_test("BGE signed: 5 >= -5 (true)",
                 3'b101, 32'h0000_0005, 32'hFFFF_FFFB, 1'b1);

        run_test("BGE signed: -5 >= 5 (false)",
                 3'b101, 32'hFFFF_FFFB, 32'h0000_0005, 1'b0);

        run_test("BGE signed: -5 >= -10 (true)",
                 3'b101, 32'hFFFF_FFFB, 32'hFFFF_FFF6, 1'b1);

        //=========================================================
        // BLTU (unsigned) tests
        //=========================================================
        run_test("BLTU unsigned: 1 < 2 (true)",
                 3'b110, 32'h0000_0001, 32'h0000_0002, 1'b1);

        run_test("BLTU unsigned: 2 < 1 (false)",
                 3'b110, 32'h0000_0002, 32'h0000_0001, 1'b0);

        // This is the classic tricky case:
        // 0x80000000 is negative signed, but very large unsigned.
        run_test("BLTU unsigned: 0x80000000 < 0x7FFFFFFF (false)",
                 3'b110, 32'h8000_0000, 32'h7FFF_FFFF, 1'b0);

        run_test("BLTU unsigned: 0x7FFFFFFF < 0x80000000 (true)",
                 3'b110, 32'h7FFF_FFFF, 32'h8000_0000, 1'b1);

        //=========================================================
        // BGEU (unsigned) tests
        //=========================================================
        run_test("BGEU unsigned: 5 >= 5 (true)",
                 3'b111, 32'h0000_0005, 32'h0000_0005, 1'b1);

        run_test("BGEU unsigned: 10 >= 5 (true)",
                 3'b111, 32'h0000_000A, 32'h0000_0005, 1'b1);

        run_test("BGEU unsigned: 5 >= 10 (false)",
                 3'b111, 32'h0000_0005, 32'h0000_000A, 1'b0);

        run_test("BGEU unsigned: 0x80000000 >= 0x7FFFFFFF (true)",
                 3'b111, 32'h8000_0000, 32'h7FFF_FFFF, 1'b1);

        //=========================================================
        // Default funct3 test (invalid funct3)
        //=========================================================
        run_test("Invalid funct3 -> take_branch must be 0",
                 3'b010, 32'h0000_0001, 32'h0000_0001, 1'b0);

        //=========================================================
        // Final Summary Report
        //=========================================================
        $display("====================================================");
        $display(" BRANCH_UNIT VERIFICATION REPORT");
        $display("====================================================");
        $display("   Total Tests   : %0d", total_tests);
        $display("   Passed        : %0d", passed_tests);
        $display("   Failed        : %0d", failed_tests);
        $display("====================================================");

        if (failed_tests == 0) begin
            $display("STATUS: ALL TESTS PASSED");
        end
        else begin
            $display("STATUS: SOME TESTS FAILED");
        end

        $display("====================================================");
        $display("");

        $finish;
    end

endmodule

Verification_Results/vcd/tb_branch_unit.vcd
$date
	Mon Mar  9 20:55:09 2026
$end
$version
	Icarus Verilog
$end
$timescale
	1ps
$end
$scope module tb_branch_unit $end
$var wire 1 ! take_branch $end
$var parameter 32 " TEST_DELAY $end
$var reg 3 # funct3 [2:0] $end
$var reg 32 $ rs1_val [31:0] $end
$var reg 32 % rs2_val [31:0] $end
$var integer 32 & failed_tests [31:0] $end
$var integer 32 ' passed_tests [31:0] $end
$var integer 32 ( total_tests [31:0] $end
$scope module dut $end
$var wire 3 ) funct3 [2:0] $end
$var wire 32 * rs1_val [31:0] $end
$var wire 32 + rs2_val [31:0] $end
$var wire 1 , lt_unsigned $end
$var wire 1 - lt_signed $end
$var wire 1 . eq $end
$var reg 1 ! take_branch $end
$upscope $end
$scope task print_divider $end
$upscope $end
$scope task run_test $end
$var reg 1 / expected_take $end
$var reg 3 0 funct3_in [2:0] $end
$var reg 1 1 got_take $end
$var reg 32 2 rs1_in [31:0] $end
$var reg 32 3 rs2_in [31:0] $end
$var reg 560 4 test_name [560:1] $end
$upscope $end
$upscope $end
$enddefinitions $end
$comment Show the parameter values. $end
$dumpall
b1010 "
$end
#0
$dumpvars
b1000010010001010101000100100000011101000111001001110101011001010010000000101000011001010111000101110101011000010110110000101001 4
b10000 3
b10000 2
x1
b0 0
1/
1.
0-
0,
b10000 +
b10000 *
b0 )
b1 (
b0 '
b0 &
b10000 %
b10000 $
b0 #
1!
$end
#2000
b1 '
11
#12000
0!
0.
1-
1,
b10001 %
b10001 +
b10 (
0/
b10001 3
b10000100100010101010001001000000110011001100001011011000111001101100101001000000010100001101110011011110111010000100000011001010111000101110101011000010110110000101001 4
#14000
b10 '
01
#24000
1!
b1 #
b1 )
b11 (
1/
b1 0
b100001001001110010001010010000001110100011100100111010101100101001000000010100001101110011011110111010000100000011001010111000101110101011000010110110000101001 4
#26000
b11 '
11
#36000
0!
1.
0-
b10101011110011011110111100000001 %
b10101011110011011110111100000001 +
0,
b10101011110011011110111100000001 $
b10101011110011011110111100000001 *
b100 (
0/
b10101011110011011110111100000001 3
b10101011110011011110111100000001 2
b100001001001110010001010010000001100110011000010110110001110011011001010010000000101000011001010111000101110101011000010110110000101001 4
#38000
b100 '
01
#48000
1!
1-
b101 %
b101 +
0.
b11111111111111111111111111111011 $
b11111111111111111111111111111011 *
b100 #
b100 )
b101 (
1/
b101 3
b11111111111111111111111111111011 2
b100 0
b1000010010011000101010000100000011100110110100101100111011011100110010101100100001110100010000000101101001101010010000000111100001000000011010100100000001010000111010001110010011101010110010100101001 4
#50000
b101 '
11
#60000
0!
1,
b11111111111111111111111111111011 %
b11111111111111111111111111111011 +
0.
0-
b101 $
b101 *
b110 (
0/
b11111111111111111111111111111011 3
b101 2
b100001001001100010101000010000001110011011010010110011101101110011001010110010000111010001000000011010100100000001111000010000000101101001101010010000000101000011001100110000101101100011100110110010100101001 4
#62000
b110 '
01
#72000
1!
1-
b11111111111111111111111111110110 $
b11111111111111111111111111110110 *
b111 (
1/
b11111111111111111111111111110110 2
b10000100100110001010100001000000111001101101001011001110110111001100101011001000011101000100000001011010011000100110000001000000011110000100000001011010011010100100000001010000111010001110010011101010110010100101001 4
#74000
b111 '
11
#84000
1!
1.
0,
b101 %
b101 +
0-
b101 $
b101 *
b101 #
b101 )
b1000 (
b101 3
b101 2
b101 0
b1000010010001110100010100100000011100110110100101100111011011100110010101100100001110100010000000110101001000000011111000111101001000000011010100100000001010000111010001110010011101010110010100101001 4
#86000
b1000 '
#96000
1!
0.
1,
b11111111111111111111111111111011 %
b11111111111111111111111111111011 +
b1001 (
b11111111111111111111111111111011 3
b100001001000111010001010010000001110011011010010110011101101110011001010110010000111010001000000011010100100000001111100011110100100000001011010011010100100000001010000111010001110010011101010110010100101001 4
#98000
b1001 '
#108000
0!
1-
b101 %
b101 +
0.
0,
b11111111111111111111111111111011 $
b11111111111111111111111111111011 *
b1010 (
0/
b101 3
b11111111111111111111111111111011 2
b10000100100011101000101001000000111001101101001011001110110111001100101011001000011101000100000001011010011010100100000001111100011110100100000001101010010000000101000011001100110000101101100011100110110010100101001 4
#110000
b1010 '
01
#120000
1!
0-
b11111111111111111111111111110110 %
b11111111111111111111111111110110 +
b1011 (
1/
b11111111111111111111111111110110 3
b1000010010001110100010100100000011100110110100101100111011011100110010101100100001110100010000000101101001101010010000000111110001111010010000000101101001100010011000000100000001010000111010001110010011101010110010100101001 4
#122000
b1011 '
11
#132000
1!
1-
b10 %
b10 +
1,
b1 $
b1 *
b110 #
b110 )
b1100 (
b10 3
b1 2
b110 0
b10000100100110001010100010101010010000001110101011011100111001101101001011001110110111001100101011001000011101000100000001100010010000000111100001000000011001000100000001010000111010001110010011101010110010100101001 4
#134000
b1100 '
#144000
0!
b1 %
b1 +
0.
0-
0,
b10 $
b10 *
b1101 (
0/
b1 3
b10 2
b1000010010011000101010001010101001000000111010101101110011100110110100101100111011011100110010101100100001110100010000000110010001000000011110000100000001100010010000000101000011001100110000101101100011100110110010100101001 4
#146000
b1101 '
01
#156000
b1111111111111111111111111111111 %
b1111111111111111111111111111111 +
1-
b10000000000000000000000000000000 $
b10000000000000000000000000000000 *
b1110 (
b1111111111111111111111111111111 3
b10000000000000000000000000000000 2
b1000010010011000101010001010101001000000111010101101110011100110110100101100111011011100110010101100100001110100010000000110000011110000011100000110000001100000011000000110000001100000011000000110000001000000011110000100000001100000111100000110111010001100100011001000110010001100100011001000110010001100010000000101000011001100110000101101100011100110110010100101001 4
#158000
b1110 '
#168000
1!
1,
b10000000000000000000000000000000 %
b10000000000000000000000000000000 +
0.
0-
b1111111111111111111111111111111 $
b1111111111111111111111111111111 *
b1111 (
1/
b10000000000000000000000000000000 3
b1111111111111111111111111111111 2
b10000100100110001010100010101010010000001110101011011100111001101101001011001110110111001100101011001000011101000100000001100000111100000110111010001100100011001000110010001100100011001000110010001100010000000111100001000000011000001111000001110000011000000110000001100000011000000110000001100000011000000100000001010000111010001110010011101010110010100101001 4
#170000
b1111 '
11
#180000
1!
1.
0,
b101 %
b101 +
b101 $
b101 *
b111 #
b111 )
b10000 (
b101 3
b101 2
b111 0
b1000010010001110100010101010101001000000111010101101110011100110110100101100111011011100110010101100100001110100010000000110101001000000011111000111101001000000011010100100000001010000111010001110010011101010110010100101001 4
#182000
b10000 '
#192000
1!
0.
b1010 $
b1010 *
b10001 (
b1010 2
b100001001000111010001010101010100100000011101010110111001110011011010010110011101101110011001010110010000111010001000000011000100110000001000000011111000111101001000000011010100100000001010000111010001110010011101010110010100101001 4
#194000
b10001 '
#204000
0!
1-
1,
b1010 %
b1010 +
0.
b101 $
b101 *
b10010 (
0/
b1010 3
b101 2
b10000100100011101000101010101010010000001110101011011100111001101101001011001110110111001100101011001000011101000100000001101010010000000111110001111010010000000110001001100000010000000101000011001100110000101101100011100110110010100101001 4
#206000
b10010 '
01
#216000
1!
b1111111111111111111111111111111 %
b1111111111111111111111111111111 +
0,
b10000000000000000000000000000000 $
b10000000000000000000000000000000 *
b10011 (
1/
b1111111111111111111111111111111 3
b10000000000000000000000000000000 2
b1000010010001110100010101010101001000000111010101101110011100110110100101100111011011100110010101100100001110100010000000110000011110000011100000110000001100000011000000110000001100000011000000110000001000000011111000111101001000000011000001111000001101110100011001000110010001100100011001000110010001100100011000100000001010000111010001110010011101010110010100101001 4
#218000
b10011 '
11
#228000
0!
1.
0-
b1 %
b1 +
0,
b1 $
b1 *
b10 #
b10 )
b10100 (
0/
b1 3
b1 2
b10 0
b10010010110111001110110011000010110110001101001011001000010000001100110011101010110111001100011011101000011001100100000001011010011111000100000011101000110000101101011011001010101111101100010011100100110000101101110011000110110100000100000011011010111010101110011011101000010000001100010011001010010000000110000 4
#230000
b10100 '
01
