src/dmem.v
//=====================================================================
// File        : dmem.v
// Author      : Prabhat Pandey
// Created On  : 16-Feb-2026
// Project     : RV32I Single-Cycle 32-bit RISC-V Processor
// Module Name : dmem
// Description :
//   This module implements Data Memory (DMEM) for an RV32I single-cycle
//   processor.
//
//   Supported operations:
//     - LW : Load word (32-bit read)
//     - SW : Store word (32-bit write)
//
// Interface:
//   Inputs:
//     - clk       : clock (writes occur on posedge)
//     - mem_read  : when 1, read data is valid on read_data
//     - mem_write : when 1, write occurs on posedge clk
//     - addr      : 32-bit byte address (from ALU)
//     - write_data: 32-bit data to store (from rs2)
//
//   Outputs:
//     - read_data : 32-bit data loaded from memory
//
// Memory Organization:
//   - This DMEM is word-addressed internally.
//   - Since RV32I LW/SW operate on 32-bit aligned addresses,
//     we use addr[31:2] as the word index.
//   - addr[1:0] are ignored (assumed 00).
//
// Notes:
//   - Read is combinational for simplicity in single-cycle CPU.
//   - Write is synchronous on rising edge of clk.
//   - If mem_read=0, read_data returns 0.
//   - If mem_write=0, no memory update occurs.
//   - Memory initialization is expected to be done at the top level or
//     testbench (simulation-only), not inside this module.
//
// Revision History:
//   - 25-Feb-2026 : updated to make it synthesis-friendly
//   - 16-Feb-2026 : Initial version
//=====================================================================

module dmem #(
    parameter DEPTH = 256                // Number of 32-bit words
)(
    input  wire        clk,
    input  wire        mem_read,
    input  wire        mem_write,
    input  wire [31:0] addr,             // Byte address
    input  wire [31:0] write_data,       // Data to store
    output reg  [31:0] read_data         // Data loaded
);

    //=================================================================
    // Memory array (word-addressed)
    //=================================================================
    reg [31:0] mem [0:DEPTH-1];

    //=================================================================
    // Word index extraction
    //=================================================================
    // We assume aligned accesses, so addr[1:0] = 00.
    // Use addr[31:2] for word indexing.
    //=================================================================
    wire [31:0] word_index;
    assign word_index = addr >> 2;

    //=================================================================
    // Combinational read
    //=================================================================
    always @(*) begin
        if (mem_read)
            read_data = mem[word_index];
        else
            read_data = 32'h0000_0000;
    end

    //=================================================================
    // Synchronous write (posedge)
    //=================================================================
    always @(posedge clk) begin
        if (mem_write)
            mem[word_index] <= write_data;
    end

endmodule

RTL_Verification/tb_dmem.v
//=====================================================================
// File        : tb_dmem.v
// Author      : Prabhat Pandey
// Created On  : 16-Feb-2026
// Project     : RV32I Single-Cycle 32-bit RISC-V Processor
// Testbench   : tb_dmem
// Description :
//   Fully self-checking testbench for dmem.v
//
// DMEM Behavior Verified:
//   1) Combinational read when mem_read=1
//   2) Synchronous write on posedge clk when mem_write=1
//   3) mem_read=0 forces read_data = 0
//   4) mem_write=0 prevents memory update
//   5) Word addressing uses addr[31:2]
//   6) No out-of-range checks in RTL (addressing is truncated by width)
//
// Verification Features:
//   - Fully self-checking
//   - Input print per test
//   - Expected output print
//   - Actual output print
//   - PASS/FAIL per test
//   - Global counters
//   - Final verification summary report
//
// Run Commands:
//   iverilog -o ./Verification_Results/result_tb_dmem ./src/dmem.v ./RTL_Verification/tb_dmem.v
//   vvp ./Verification_Results/result_tb_dmem
//=====================================================================

`timescale 1ns/1ps

module tb_dmem;

    //=============================================================
    // Parameters (must match DUT config)
    //=============================================================
    localparam DEPTH = 16; // keep small for test visibility
    localparam integer TEST_DELAY = 10; // ns between tests for waveform visibility

    //=============================================================
    // DUT Signals
    //=============================================================
    reg         clk;
    reg         mem_read;
    reg         mem_write;
    reg  [31:0] addr;
    reg  [31:0] write_data;
    wire [31:0] read_data;

    //=============================================================
    // Instantiate DUT
    //=============================================================
    dmem #(
        .DEPTH(DEPTH)
    ) dut (
        .clk        (clk),
        .mem_read   (mem_read),
        .mem_write  (mem_write),
        .addr       (addr),
        .write_data (write_data),
        .read_data  (read_data)
    );

    //=============================================================
    // Global Counters
    //=============================================================
    integer total_tests;
    integer passed_tests;
    integer failed_tests;
    integer i;

    //=============================================================
    // VCD Dump (for GTKWave)
    //=============================================================
    initial begin
        $dumpfile("Verification_Results/vcd/tb_dmem.vcd");
        $dumpvars(0, tb_dmem);
    end

    //=============================================================
    // Clock Generation (10ns period)
    //=============================================================
    initial begin
        clk = 1'b0;
        forever #5 clk = ~clk;
    end

    //=============================================================
    // Task: Divider
    //=============================================================
    task print_divider;
        begin
            $display("----------------------------------------------------------------");
        end
    endtask

    //=============================================================
    // Task: Run One Read Test
    //=============================================================
    task run_read_test;
        input [8*70:1] test_name;
        input          mem_read_in;
        input [31:0]   addr_in;
        input [31:0]   expected_read;

        reg [31:0] got_read;
        begin
            total_tests = total_tests + 1;

            print_divider();
            $display("TEST : %s", test_name);

            // Apply inputs
            mem_read   = mem_read_in;
            mem_write  = 1'b0;
            addr       = addr_in;
            write_data = 32'h0000_0000;

            #2; // settle combinational read
            got_read = read_data;

            // Print Inputs
            $display("Inputs:");
            $display("   mem_read   = %0d", mem_read_in);
            $display("   mem_write  = %0d", 1'b0);
            $display("   addr       = %08h", addr_in);
            $display("   word_index = %0d", (addr_in >> 2));

            // Print Expected
            $display("");
            $display("Expected:");
            $display("   read_data  = %08h", expected_read);

            // Print Got
            $display("");
            $display("Got:");
            $display("   read_data  = %08h", got_read);

            // Compare
            if (got_read === expected_read) begin
                passed_tests = passed_tests + 1;
                $display("STATUS: PASS");
            end
            else begin
                failed_tests = failed_tests + 1;
                $display("STATUS: FAIL");
            end

            print_divider();
            $display("");

            #(TEST_DELAY);
        end
    endtask

    //=============================================================
    // Task: Run One Write + Readback Test
    //=============================================================
    task run_write_readback_test;
        input [8*70:1] test_name;
        input          mem_write_in;
        input [31:0]   addr_in;
        input [31:0]   wd_in;
        input [31:0]   expected_after;

        reg [31:0] got_read;
        begin
            total_tests = total_tests + 1;

            print_divider();
            $display("TEST : %s", test_name);

            // Step 1: Apply write signals
            mem_read   = 1'b0;
            mem_write  = mem_write_in;
            addr       = addr_in;
            write_data = wd_in;

            // Commit on posedge
            @(posedge clk);
            #1;

            // Step 2: Read back
            mem_write = 1'b0;
            mem_read  = 1'b1;
            #2;

            got_read = read_data;

            // Print Inputs
            $display("Inputs:");
            $display("   mem_write  = %0d", mem_write_in);
            $display("   mem_read   = %0d", 1'b1);
            $display("   addr       = %08h", addr_in);
            $display("   word_index = %0d", (addr_in >> 2));
            $display("   write_data = %08h", wd_in);

            // Print Expected
            $display("");
            $display("Expected:");
            $display("   read_data  = %08h", expected_after);

            // Print Got
            $display("");
            $display("Got:");
            $display("   read_data  = %08h", got_read);

            // Compare
            if (got_read === expected_after) begin
                passed_tests = passed_tests + 1;
                $display("STATUS: PASS");
            end
            else begin
                failed_tests = failed_tests + 1;
                $display("STATUS: FAIL");
            end

            print_divider();
            $display("");

            #(TEST_DELAY);
        end
    endtask

    //=============================================================
    // Main Test Sequence
    //=============================================================
    initial begin

        // Init counters
        total_tests  = 0;
        passed_tests = 0;
        failed_tests = 0;

        // Init inputs
        mem_read   = 1'b0;
        mem_write  = 1'b0;
        addr       = 32'h0000_0000;
        write_data = 32'h0000_0000;

        // Clear memory (simulation-only)
        for (i = 0; i < DEPTH; i = i + 1)
            dut.mem[i] = 32'h0000_0000;

        $display("====================================================");
        $display(" DMEM VERIFICATION STARTED — Author: Prabhat Pandey");
        $display("====================================================");
        $display("");

        //=========================================================
        // TEST 1: Read from address 0 (initial memory = 0)
        //=========================================================
        run_read_test("Initial read @ addr=0 should be 0",
                      1'b1, 32'h0000_0000, 32'h0000_0000);

        //=========================================================
        // TEST 2: Write then read back @ addr=0
        //=========================================================
        run_write_readback_test("Write 0xDEADBEEF @ addr=0, read back",
                                1'b1, 32'h0000_0000, 32'hDEAD_BEEF,
                                32'hDEAD_BEEF);

        //=========================================================
        // TEST 3: Write then read back @ addr=4 (word index 1)
        //=========================================================
        run_write_readback_test("Write 0x12345678 @ addr=4, read back",
                                1'b1, 32'h0000_0004, 32'h1234_5678,
                                32'h1234_5678);

        //=========================================================
        // TEST 4: Verify addr=0 still has old data
        //=========================================================
        run_read_test("Read @ addr=0 must still be 0xDEADBEEF",
                      1'b1, 32'h0000_0000, 32'hDEAD_BEEF);

        //=========================================================
        // TEST 5: mem_write=0 should not update memory
        //=========================================================
        run_write_readback_test("Write disabled (mem_write=0), addr=8 must remain 0",
                                1'b0, 32'h0000_0008, 32'hAAAA_AAAA,
                                32'h0000_0000);

        //=========================================================
        // TEST 6: mem_read=0 forces read_data=0 even if memory has data
        //=========================================================
        run_read_test("mem_read=0 must force read_data=0 (even if mem contains data)",
                      1'b0, 32'h0000_0000, 32'h0000_0000);

        //=========================================================
        // Final Summary Report
        //=========================================================
        $display("====================================================");
        $display(" DMEM VERIFICATION REPORT");
        $display("====================================================");
        $display("   Total Tests   : %0d", total_tests);
        $display("   Passed        : %0d", passed_tests);
        $display("   Failed        : %0d", failed_tests);
        $display("====================================================");

        if (failed_tests == 0) begin
            $display("STATUS: ALL TESTS PASSED");
        end
        else begin
            $display("STATUS: SOME TESTS FAILED");
        end

        $display("====================================================");
        $display("");

        $finish;
    end

endmodule

Verification_Results/vcd/tb_dmem.vcd
$date
	Mon Mar  9 19:13:53 2026
$end
$version
	Icarus Verilog
$end
$timescale
	1ps
$end
$scope module tb_dmem $end
$var wire 32 ! read_data [31:0] $end
$var parameter 32 " DEPTH $end
$var parameter 32 # TEST_DELAY $end
$var reg 32 $ addr [31:0] $end
$var reg 1 % clk $end
$var reg 1 & mem_read $end
$var reg 1 ' mem_write $end
$var reg 32 ( write_data [31:0] $end
$var integer 32 ) failed_tests [31:0] $end
$var integer 32 * i [31:0] $end
$var integer 32 + passed_tests [31:0] $end
$var integer 32 , total_tests [31:0] $end
$scope module dut $end
$var wire 32 - addr [31:0] $end
$var wire 1 % clk $end
$var wire 1 & mem_read $end
$var wire 1 ' mem_write $end
$var wire 32 . write_data [31:0] $end
$var wire 32 / word_index [31:0] $end
$var parameter 32 0 DEPTH $end
$var reg 32 1 read_data [31:0] $end
$upscope $end
$scope task print_divider $end
$upscope $end
$scope task run_read_test $end
$var reg 32 2 addr_in [31:0] $end
$var reg 32 3 expected_read [31:0] $end
$var reg 32 4 got_read [31:0] $end
$var reg 1 5 mem_read_in $end
$var reg 560 6 test_name [560:1] $end
$upscope $end
$scope task run_write_readback_test $end
$var reg 32 7 addr_in [31:0] $end
$var reg 32 8 expected_after [31:0] $end
$var reg 32 9 got_read [31:0] $end
$var reg 1 : mem_write_in $end
$var reg 560 ; test_name [560:1] $end
$var reg 32 < wd_in [31:0] $end
$upscope $end
$upscope $end
$enddefinitions $end
$comment Show the parameter values. $end
$dumpall
b10000 0
b1010 #
b10000 "
$end
#0
$dumpvars
bx <
bx ;
x:
bx 9
bx 8
bx 7
b10010010110111001101001011101000110100101100001011011000010000001110010011001010110000101100100001000000100000000100000011000010110010001100100011100100011110100110000001000000111001101101000011011110111010101101100011001000010000001100010011001010010000000110000 6
15
bx 4
b0 3
b0 2
b0 1
b0 /
b0 .
b0 -
b1 ,
b0 +
b10000 *
b0 )
b0 (
0'
1&
0%
b0 $
b0 !
$end
#2000
b1 +
b0 4
#5000
1%
#10000
0%
#12000
b11011110101011011011111011101111 (
b11011110101011011011111011101111 .
1'
0&
b10 ,
b11011110101011011011111011101111 8
b11011110101011011011111011101111 <
b0 7
1:
b10101110111001001101001011101000110010100100000001100000111100001000100010001010100000101000100010000100100010101000101010001100010000001000000001000000110000101100100011001000111001000111101001100000010110000100000011100100110010101100001011001000010000001100010011000010110001101101011 ;
#15000
1%
#16000
b11011110101011011011111011101111 !
b11011110101011011011111011101111 1
1&
0'
#18000
b10 +
b11011110101011011011111011101111 9
#20000
0%
#25000
1%
#28000
b1 /
b0 !
b0 1
b10010001101000101011001111000 (
b10010001101000101011001111000 .
b100 $
b100 -
1'
0&
b11 ,
b10010001101000101011001111000 8
b10010001101000101011001111000 <
b100 7
b10101110111001001101001011101000110010100100000001100000111100000110001001100100011001100110100001101010011011000110111001110000010000001000000001000000110000101100100011001000111001000111101001101000010110000100000011100100110010101100001011001000010000001100010011000010110001101101011 ;
#30000
0%
#35000
1%
#36000
b10010001101000101011001111000 !
b10010001101000101011001111000 1
1&
0'
#38000
b11 +
b10010001101000101011001111000 9
#40000
0%
#45000
1%
#48000
b11011110101011011011111011101111 !
b11011110101011011011111011101111 1
b0 /
b0 (
b0 .
b0 $
b0 -
b100 ,
b11011110101011011011111011101111 3
b101001001100101011000010110010000100000010000000010000001100001011001000110010001110010001111010011000000100000011011010111010101110011011101000010000001110011011101000110100101101100011011000010000001100010011001010010000000110000011110000100010001000101010000010100010001000010010001010100010101000110 6
#50000
b100 +
b11011110101011011011111011101111 4
0%
#55000
1%
#60000
b10 /
b0 !
b0 1
0%
b10101010101010101010101010101010 (
b10101010101010101010101010101010 .
b1000 $
b1000 -
0&
b101 ,
b0 8
b10101010101010101010101010101010 <
b1000 7
0:
b101011101110010011010010111010001100101001000000110010001101001011100110110000101100010011011000110010101100100001000000010100001101101011001010110110101011111011101110111001001101001011101000110010100111101001100000010100100101100001000000110000101100100011001000111001000111101001110000010000001101101011101010111001101110100001000000111001001100101011011010110000101101001011011100010000000110000 ;
#65000
1%
#66000
1&
#68000
b101 +
b0 9
#70000
0%
#75000
1%
#78000
b0 /
b0 (
b0 .
b0 $
b0 -
0&
b110 ,
b0 3
05
b1101101011001010110110101011111011100100110010101100001011001000011110100110000001000000110110101110101011100110111010000100000011001100110111101110010011000110110010100100000011100100110010101100001011001000101111101100100011000010111010001100001001111010011000000100000001010000110010101110110011001010110111000100000011010010110011000100000011011010110010101101101001000000110001101101111011011100111010001100001011010010110111001110011001000000110010001100001011101000110000100101001 6
#80000
b110 +
b0 4
0%
