src/imm_gen.v
//=====================================================================
// File        : imm_gen.v
// Author      : Prabhat Pandey
// Created On  : 15-Feb-2026
// Project     : RV32I Single-Cycle 32-bit RISC-V Processor
// Module Name : imm_gen
// Description :
//   This module generates all immediate formats required for RV32I.
//
//   RISC-V RV32I immediate types supported:
//     - I-type : used by OP-IMM, LOAD, JALR
//     - S-type : used by STORE
//     - B-type : used by BRANCH
//     - U-type : used by LUI, AUIPC
//     - J-type : used by JAL
//
// Inputs:
//   - instr : full 32-bit instruction
//
// Outputs:
//   - imm_i : sign-extended I-type immediate
//   - imm_s : sign-extended S-type immediate
//   - imm_b : sign-extended B-type immediate (already shifted by 1)
//   - imm_u : U-type immediate (upper 20 bits << 12)
//   - imm_j : sign-extended J-type immediate (already shifted by 1)
//
// Notes (VERY IMPORTANT):
//   - B-type and J-type immediates in RISC-V are always multiples of 2,
//     meaning bit0 is always 0.
//     So imm_b and imm_j are produced already with bit0 = 0.
//   - All sign extensions are done to 32-bit.
//   - This module is purely combinational.
//
// Revision History:
//   - 16-Feb-2026 : Rewritten from single-output version to full RV32I
//                   multi-output version for complete CPU integration.
//   - 15-Feb-2026 : Initial version
//=====================================================================

module imm_gen (
    input  wire [31:0] instr,     // Full 32-bit instruction

    output wire [31:0] imm_i,      // I-type immediate
    output wire [31:0] imm_s,      // S-type immediate
    output wire [31:0] imm_b,      // B-type immediate
    output wire [31:0] imm_u,      // U-type immediate
    output wire [31:0] imm_j       // J-type immediate
);

    //=================================================================
    // I-type Immediate (12-bit signed)
    // Format:
    //   imm[11:0] = instr[31:20]
    //
    // Used by:
    //   - addi, andi, ori, xori, slti, sltiu
    //   - slli, srli, srai  (shamt in imm[4:0])
    //   - lw
    //   - jalr
    //=================================================================
    assign imm_i = {{20{instr[31]}}, instr[31:20]};

    //=================================================================
    // S-type Immediate (12-bit signed)
    // Format:
    //   imm[11:5] = instr[31:25]
    //   imm[4:0]  = instr[11:7]
    //
    // Used by:
    //   - sw
    //=================================================================
    assign imm_s = {{20{instr[31]}}, instr[31:25], instr[11:7]};

    //=================================================================
    // B-type Immediate (13-bit signed, branch offsets)
    // Format (NOTE bit0 = 0):
    //   imm[12]   = instr[31]
    //   imm[11]   = instr[7]
    //   imm[10:5] = instr[30:25]
    //   imm[4:1]  = instr[11:8]
    //   imm[0]    = 0
    //
    // Used by:
    //   - beq, bne, blt, bge, bltu, bgeu
    //
    // IMPORTANT:
    //   - The produced imm_b is already shifted left by 1.
    //=================================================================
    assign imm_b = {
        {19{instr[31]}},   // sign extension
        instr[31],         // imm[12]
        instr[7],          // imm[11]
        instr[30:25],      // imm[10:5]
        instr[11:8],       // imm[4:1]
        1'b0               // imm[0]
    };

    //=================================================================
    // U-type Immediate (upper 20 bits)
    // Format:
    //   imm[31:12] = instr[31:12]
    //   imm[11:0]  = 0
    //
    // Used by:
    //   - lui
    //   - auipc
    //=================================================================
    assign imm_u = {instr[31:12], 12'b0};

    //=================================================================
    // J-type Immediate (21-bit signed, jump offsets)
    // Format (NOTE bit0 = 0):
    //   imm[20]   = instr[31]
    //   imm[19:12]= instr[19:12]
    //   imm[11]   = instr[20]
    //   imm[10:1] = instr[30:21]
    //   imm[0]    = 0
    //
    // Used by:
    //   - jal
    //
    // IMPORTANT:
    //   - The produced imm_j is already shifted left by 1.
    //=================================================================
    assign imm_j = {
        {11{instr[31]}},   // sign extension
        instr[31],         // imm[20]
        instr[19:12],      // imm[19:12]
        instr[20],         // imm[11]
        instr[30:21],      // imm[10:1]
        1'b0               // imm[0]
    };

endmodule

RTL_Verification/tb_imm_gen.v
//=====================================================================
// File        : tb_imm_gen.v
// Author      : Prabhat Pandey
// Created On  : 15-Feb-2026
// Project     : RV32I Single-Cycle 32-bit RISC-V Processor
// Testbench   : tb_imm_gen
// Description :
//   Fully self-checking testbench for imm_gen.v
//
//   This testbench verifies correct immediate extraction and sign
//   extension for RV32I instruction formats:
//
//     1) I-type (OP-IMM, LOAD, JALR)
//     2) S-type (STORE)
//     3) B-type (BRANCH)  [shift-left by 1, imm[0]=0]
//     4) U-type (LUI, AUIPC)
//     5) J-type (JAL)     [shift-left by 1, imm[0]=0]
//
// Verification Features:
//   - Fully self-checking
//   - Input print (instruction, opcode)
//   - Expected output print
//   - Actual output print
//   - PASS/FAIL per test case
//   - Global counters
//   - Final verification summary report
//
// Run Commands:
//   iverilog -o ./Verification_Results/result_tb_imm_gen ./src/imm_gen.v ./RTL_Verification/tb_imm_gen.v
//   vvp ./Verification_Results/result_tb_imm_gen
//=====================================================================

`timescale 1ns/1ps

module tb_imm_gen;

    //=============================================================
    // Testbench Parameters
    //=============================================================
    localparam integer TEST_DELAY = 10; // ns between tests for waveform visibility

    //=============================================================
    // DUT Signals
    //=============================================================
    reg  [31:0] instr;
    wire [31:0] imm_i;
    wire [31:0] imm_s;
    wire [31:0] imm_b;
    wire [31:0] imm_u;
    wire [31:0] imm_j;

    //=============================================================
    // Instantiate DUT
    //=============================================================
    imm_gen dut (
        .instr (instr),
        .imm_i (imm_i),
        .imm_s (imm_s),
        .imm_b (imm_b),
        .imm_u (imm_u),
        .imm_j (imm_j)
    );

    //=============================================================
    // Global Verification Counters
    //=============================================================
    integer total_tests;
    integer passed_tests;
    integer failed_tests;

    //=============================================================
    // VCD Dump (for GTKWave)
    //=============================================================
    initial begin
        $dumpfile("Verification_Results/vcd/tb_imm_gen.vcd");
        $dumpvars(0, tb_imm_gen);
    end

    //=============================================================
    // Task: Divider
    //=============================================================
    task print_divider;
        begin
            $display("----------------------------------------------------------------");
        end
    endtask

    //=============================================================
    // Function: Get opcode from instruction
    //=============================================================
    function [6:0] get_opcode;
        input [31:0] ins;
        begin
            get_opcode = ins[6:0];
        end
    endfunction

    //=============================================================
    // Task: Run One Test Case
    //=============================================================
    task run_test;
        input [8*70:1] test_name;
        input [31:0]   instr_in;
        input [31:0]   expected_imm;

        reg [31:0] got_imm;
        reg [6:0]  opc;
        begin
            total_tests = total_tests + 1;

            print_divider();
            $display("TEST : %s", test_name);

            instr = instr_in;
            #2; // combinational settle

            opc = get_opcode(instr_in);

            // Select the correct immediate based on opcode
            case (opc)
                7'b0010011, // OP-IMM
                7'b0000011, // LOAD
                7'b1100111: // JALR
                    got_imm = imm_i;

                7'b0100011: // STORE
                    got_imm = imm_s;

                7'b1100011: // BRANCH
                    got_imm = imm_b;

                7'b0110111, // LUI
                7'b0010111: // AUIPC
                    got_imm = imm_u;

                7'b1101111: // JAL
                    got_imm = imm_j;

                default:
                    got_imm = 32'h0000_0000;
            endcase

            // Print Inputs
            $display("Inputs:");
            $display("   instr   = %08h", instr_in);
            $display("   opcode  = %07b", opc);

            // Print Expected
            $display("");
            $display("Expected:");
            $display("   imm_out = %08h", expected_imm);

            // Print Got
            $display("");
            $display("Got:");
            $display("   imm_out = %08h", got_imm);

            // Compare
            if (got_imm === expected_imm) begin
                passed_tests = passed_tests + 1;
                $display("STATUS: PASS");
            end
            else begin
                failed_tests = failed_tests + 1;
                $display("STATUS: FAIL");
            end

            print_divider();
            $display("");

            #(TEST_DELAY);
        end
    endtask

    //=============================================================
    // Helper: Build Instructions (Minimal Encodings)
    //=============================================================
    // We only care about immediate bit positions and opcode.
    // The remaining fields (rd, rs1, rs2, funct3) can be anything.
    //=============================================================

    //=============================================================
    // Main Test Sequence
    //=============================================================
    initial begin

        // Init counters
        total_tests  = 0;
        passed_tests = 0;
        failed_tests = 0;

        // Init input
        instr = 32'h0000_0000;

        $display("====================================================");
        $display(" IMM_GEN VERIFICATION STARTED — Author: Prabhat Pandey");
        $display("====================================================");
        $display("");

        //=========================================================
        // I-TYPE TESTS (opcode = 0010011)
        // imm = instr[31:20]
        //=========================================================

        // I-type imm = +5
        // instr[31:20] = 0x005
        run_test("I-type imm = +5 (addi style)",
                 {12'h005, 5'd1, 3'b000, 5'd2, 7'b0010011},
                 32'h0000_0005);

        // I-type imm = -1 (0xFFF)
        run_test("I-type imm = -1",
                 {12'hFFF, 5'd1, 3'b000, 5'd2, 7'b0010011},
                 32'hFFFF_FFFF);

        // I-type imm = -2048 (min 12-bit signed)
        run_test("I-type imm = -2048 (min)",
                 {12'h800, 5'd1, 3'b000, 5'd2, 7'b0010011},
                 32'hFFFF_F800);

        // I-type imm = +2047 (max 12-bit signed)
        run_test("I-type imm = +2047 (max)",
                 {12'h7FF, 5'd1, 3'b000, 5'd2, 7'b0010011},
                 32'h0000_07FF);

        //=========================================================
        // S-TYPE TESTS (opcode = 0100011)
        // imm = {instr[31:25], instr[11:7]}
        //=========================================================

        // S-type imm = +16 (0x010)
        // imm[11:5]=0, imm[4:0]=10000
        run_test("S-type imm = +16 (sw style)",
                 {7'b0000000, 5'd3, 5'd2, 3'b010, 5'b10000, 7'b0100011},
                 32'h0000_0010);

        // S-type imm = -1 (0xFFF)
        run_test("S-type imm = -1",
                 {7'b1111111, 5'd3, 5'd2, 3'b010, 5'b11111, 7'b0100011},
                 32'hFFFF_FFFF);

        // S-type imm = -2048 (0x800)
        // imm[11]=1, others 0
        run_test("S-type imm = -2048 (min)",
                 {7'b1000000, 5'd3, 5'd2, 3'b010, 5'b00000, 7'b0100011},
                 32'hFFFF_F800);

        //=========================================================
        // B-TYPE TESTS (opcode = 1100011)
        //
        // imm encoding:
        //   imm[12]   = instr[31]
        //   imm[11]   = instr[7]
        //   imm[10:5] = instr[30:25]
        //   imm[4:1]  = instr[11:8]
        //   imm[0]    = 0
        //=========================================================

        // B-type imm = +16
        // +16 in binary = 0000 0001 0000
        // imm[4:1] = 1000, imm[10:5]=000000, imm[11]=0, imm[12]=0
        run_test("B-type imm = +16 (branch forward)",
                 {
                   1'b0,          // instr[31] imm[12]
                   6'b000000,     // instr[30:25] imm[10:5]
                   5'd2,          // rs2
                   5'd1,          // rs1
                   3'b000,        // funct3
                   4'b1000,       // instr[11:8] imm[4:1]
                   1'b0,          // instr[7] imm[11]
                   7'b1100011     // opcode
                 },
                 32'h0000_0010);

        // B-type imm = -16
        // -16 = 0xFFFF_FFF0
        // imm bits represent 13-bit signed value with bit0=0.
        run_test("B-type imm = -16 (branch backward)",
                 {
                   1'b1,          // imm[12]
                   6'b111111,     // imm[10:5]
                   5'd2,
                   5'd1,
                   3'b000,
                   4'b1000,       // imm[4:1]
                   1'b1,          // imm[11]
                   7'b1100011
                 },
                 32'hFFFF_FFF0);

        // B-type imm = +4 (smallest meaningful forward branch)
        // +4 => imm[4:1]=0010
        run_test("B-type imm = +4 (branch forward)",
                 {
                   1'b0,
                   6'b000000,
                   5'd2,
                   5'd1,
                   3'b000,
                   4'b0010,
                   1'b0,
                   7'b1100011
                 },
                 32'h0000_0004);

        //=========================================================
        // U-TYPE TESTS (opcode = 0110111 LUI, 0010111 AUIPC)
        // imm = instr[31:12] << 12
        //=========================================================

        run_test("U-type imm (LUI) = 0x12345000",
                 {20'h12345, 5'd1, 7'b0110111},
                 32'h1234_5000);

        run_test("U-type imm (AUIPC) = 0xABCDE000",
                 {20'hABCDE, 5'd1, 7'b0010111},
                 32'hABCDE_000);

        //=========================================================
        // J-TYPE TESTS (opcode = 1101111)
        //
        // imm encoding:
        //   imm[20]   = instr[31]
        //   imm[19:12]= instr[19:12]
        //   imm[11]   = instr[20]
        //   imm[10:1] = instr[30:21]
        //   imm[0]    = 0
        //=========================================================

        // J-type imm = +32
        // +32 => 0x00000020
        // imm[10:1] should represent 16 (since shift left by 1)
        // imm[10:1] = 0000010000 (16)
        run_test("J-type imm = +32 (jal forward)",
                 {
                   1'b0,          // instr[31] imm[20]
                   10'b0000010000,// instr[30:21] imm[10:1]
                   1'b0,          // instr[20] imm[11]
                   8'b00000000,   // instr[19:12] imm[19:12]
                   5'd1,          // rd
                   7'b1101111     // opcode
                 },
                 32'h0000_0020);

        // J-type imm = -32
        // -32 => 0xFFFF_FFE0
        run_test("J-type imm = -32 (jal backward)",
                 {
                   1'b1,          // imm[20]
                   10'b1111110000,// imm[10:1]
                   1'b1,          // imm[11]
                   8'b11111111,   // imm[19:12]
                   5'd1,
                   7'b1101111
                 },
                 32'hFFFF_FFE0);

        //=========================================================
        // Default opcode test (should output 0)
        //=========================================================
        run_test("Default case (unknown opcode) -> imm=0",
                 32'hFFFFFFFF,
                 32'h0000_0000);

        //=========================================================
        // Final Summary Report
        //=========================================================
        $display("====================================================");
        $display(" IMM_GEN VERIFICATION REPORT");
        $display("====================================================");
        $display("   Total Tests   : %0d", total_tests);
        $display("   Passed        : %0d", passed_tests);
        $display("   Failed        : %0d", failed_tests);
        $display("====================================================");

        if (failed_tests == 0) begin
            $display("STATUS: ALL TESTS PASSED");
        end
        else begin
            $display("STATUS: SOME TESTS FAILED");
        end

        $display("====================================================");
        $display("");

        $finish;
    end

endmodule

Verification_Results/vcd/tb_imm_gen.vcd
$date
	Mon Mar  9 19:13:53 2026
$end
$version
	Icarus Verilog
$end
$timescale
	1ps
$end
$scope module tb_imm_gen $end
$var wire 32 ! imm_u [31:0] $end
$var wire 32 " imm_s [31:0] $end
$var wire 32 # imm_j [31:0] $end
$var wire 32 $ imm_i [31:0] $end
$var wire 32 % imm_b [31:0] $end
$var parameter 32 & TEST_DELAY $end
$var reg 32 ' instr [31:0] $end
$var integer 32 ( failed_tests [31:0] $end
$var integer 32 ) passed_tests [31:0] $end
$var integer 32 * total_tests [31:0] $end
$scope function get_opcode $end
$var reg 32 + ins [31:0] $end
$upscope $end
$scope module dut $end
$var wire 32 , instr [31:0] $end
$var wire 32 - imm_u [31:0] $end
$var wire 32 . imm_s [31:0] $end
$var wire 32 / imm_j [31:0] $end
$var wire 32 0 imm_i [31:0] $end
$var wire 32 1 imm_b [31:0] $end
$upscope $end
$scope task print_divider $end
$upscope $end
$scope task run_test $end
$var reg 32 2 expected_imm [31:0] $end
$var reg 32 3 got_imm [31:0] $end
$var reg 32 4 instr_in [31:0] $end
$var reg 7 5 opc [6:0] $end
$var reg 560 6 test_name [560:1] $end
$upscope $end
$upscope $end
$enddefinitions $end
$comment Show the parameter values. $end
$dumpall
b1010 &
$end
#0
$dumpvars
b1001001001011010111010001111001011100000110010100100000011010010110110101101101001000000011110100100000001010110011010100100000001010000110000101100100011001000110100100100000011100110111010001111001011011000110010100101001 6
bx 5
b10100001000000100010011 4
bx 3
b101 2
b10 1
b101 0
b1000100000000100 /
b10 .
b10100001000000000000000 -
b10100001000000100010011 ,
bx +
b1 *
b0 )
b0 (
b10100001000000100010011 '
b10 %
b101 $
b1000100000000100 #
b10 "
b10100001000000000000000 !
$end
#2000
b1 )
b101 3
b10011 5
b10100001000000100010011 +
#12000
b11111111111111111111111111111111 $
b11111111111111111111111111111111 0
b11111111111111111111111111100010 "
b11111111111111111111111111100010 .
b11111111111111111111011111100010 %
b11111111111111111111011111100010 1
b11111111111100001000000000000000 !
b11111111111100001000000000000000 -
b11111111111100001000111111111110 #
b11111111111100001000111111111110 /
b11111111111100001000000100010011 '
b11111111111100001000000100010011 ,
b10 *
b11111111111111111111111111111111 2
b11111111111100001000000100010011 4
b10010010010110101110100011110010111000001100101001000000110100101101101011011010010000000111101001000000010110100110001 6
#14000
b10 )
b11111111111111111111111111111111 3
b11111111111100001000000100010011 +
#24000
b11111111111111111111100000000000 $
b11111111111111111111100000000000 0
b11111111111111111111100000000010 "
b11111111111111111111100000000010 .
b11111111111111111111000000000010 %
b11111111111111111111000000000010 1
b10000000000000001000000000000000 !
b10000000000000001000000000000000 -
b11111111111100001000000000000000 #
b11111111111100001000000000000000 /
b10000000000000001000000100010011 '
b10000000000000001000000100010011 ,
b11 *
b11111111111111111111100000000000 2
b10000000000000001000000100010011 4
b10010010010110101110100011110010111000001100101001000000110100101101101011011010010000000111101001000000010110100110010001100000011010000111000001000000010100001101101011010010110111000101001 6
#26000
b11 )
b11111111111111111111100000000000 3
b10000000000000001000000100010011 +
#36000
b11111111111 $
b11111111111 0
b11111100010 "
b11111100010 .
b11111100010 %
b11111100010 1
b1111111111100001000000000000000 !
b1111111111100001000000000000000 -
b1000111111111110 #
b1000111111111110 /
b1111111111100001000000100010011 '
b1111111111100001000000100010011 ,
b100 *
b11111111111 2
b1111111111100001000000100010011 4
b10010010010110101110100011110010111000001100101001000000110100101101101011011010010000000111101001000000010101100110010001100000011010000110111001000000010100001101101011000010111100000101001 6
#38000
b100 )
b11111111111 3
b1111111111100001000000100010011 +
#48000
b11 $
b11 0
b10000 "
b10000 .
b10000 %
b10000 1
b1100010010000000000000 !
b1100010010000000000000 -
b10010100000000010 #
b10010100000000010 /
b1100010010100000100011 '
b1100010010100000100011 ,
b101 *
b10000 2
b1100010010100000100011 4
b10100110010110101110100011110010111000001100101001000000110100101101101011011010010000000111101001000000010101100110001001101100010000000101000011100110111011100100000011100110111010001111001011011000110010100101001 6
#50000
b101 )
b10000 3
b100011 5
b1100010010100000100011 +
#60000
b11111111111111111111111111100011 $
b11111111111111111111111111100011 0
b11111111111111111111111111111111 "
b11111111111111111111111111111111 .
b11111111111111111111111111111110 %
b11111111111111111111111111111110 1
b11111110001100010010000000000000 !
b11111110001100010010000000000000 -
b11111111111100010010111111100010 #
b11111111111100010010111111100010 /
b11111110001100010010111110100011 '
b11111110001100010010111110100011 ,
b110 *
b11111111111111111111111111111111 2
b11111110001100010010111110100011 4
b10100110010110101110100011110010111000001100101001000000110100101101101011011010010000000111101001000000010110100110001 6
#62000
b110 )
b11111111111111111111111111111111 3
b11111110001100010010111110100011 +
#72000
b11111111111111111111100000000011 $
b11111111111111111111100000000011 0
b11111111111111111111100000000000 "
b11111111111111111111100000000000 .
b11111111111111111111000000000000 %
b11111111111111111111000000000000 1
b10000000001100010010000000000000 !
b10000000001100010010000000000000 -
b11111111111100010010100000000010 #
b11111111111100010010100000000010 /
b10000000001100010010000000100011 '
b10000000001100010010000000100011 ,
b111 *
b11111111111111111111100000000000 2
b10000000001100010010000000100011 4
b10100110010110101110100011110010111000001100101001000000110100101101101011011010010000000111101001000000010110100110010001100000011010000111000001000000010100001101101011010010110111000101001 6
#74000
b111 )
b11111111111111111111100000000000 3
b10000000001100010010000000100011 +
#84000
b10 $
b10 0
b10000 "
b10000 .
b10000 %
b10000 1
b1000001000000000000000 !
b1000001000000000000000 -
b1000000000000010 #
b1000000000000010 /
b1000001000100001100011 '
b1000001000100001100011 ,
b1000 *
b10000 2
b1000001000100001100011 4
b10000100010110101110100011110010111000001100101001000000110100101101101011011010010000000111101001000000010101100110001001101100010000000101000011000100111001001100001011011100110001101101000001000000110011001101111011100100111011101100001011100100110010000101001 6
#86000
b1000 )
b10000 3
b1100011 5
b1000001000100001100011 +
#96000
b11111111111111111111111111100010 $
b11111111111111111111111111100010 0
b11111111111111111111111111110001 "
b11111111111111111111111111110001 .
b11111111111111111111111111110000 %
b11111111111111111111111111110000 1
b11111110001000001000000000000000 !
b11111110001000001000000000000000 -
b11111111111100001000011111100010 #
b11111111111100001000011111100010 /
b11111110001000001000100011100011 '
b11111110001000001000100011100011 ,
b1001 *
b11111111111111111111111111110000 2
b11111110001000001000100011100011 4
b1000010001011010111010001111001011100000110010100100000011010010110110101101101001000000011110100100000001011010011000100110110001000000010100001100010011100100110000101101110011000110110100000100000011000100110000101100011011010110111011101100001011100100110010000101001 6
#98000
b1001 )
b11111111111111111111111111110000 3
b11111110001000001000100011100011 +
#108000
b10 $
b10 0
b100 "
b100 .
b100 %
b100 1
b1000001000000000000000 !
b1000001000000000000000 -
b1000000000000010 #
b1000000000000010 /
b1000001000001001100011 '
b1000001000001001100011 ,
b1010 *
b100 2
b1000001000001001100011 4
b100001000101101011101000111100101110000011001010010000001101001011011010110110100100000001111010010000000101011001101000010000000101000011000100111001001100001011011100110001101101000001000000110011001101111011100100111011101100001011100100110010000101001 6
#110000
b1010 )
b100 3
b1000001000001001100011 +
#120000
b100100011 $
b100100011 0
b100100001 "
b100100001 .
b100100100000 %
b100100100000 1
b10010001101000101000000000000 !
b10010001101000101000000000000 -
b1000101100100100010 #
b1000101100100100010 /
b10010001101000101000010110111 '
b10010001101000101000010110111 ,
b1011 *
b10010001101000101000000000000 2
b10010001101000101000010110111 4
b101010100101101011101000111100101110000011001010010000001101001011011010110110100100000001010000100110001010101010010010010100100100000001111010010000000110000011110000011000100110010001100110011010000110101001100000011000000110000 6
#122000
b1011 )
b10010001101000101000000000000 3
b110111 5
b10010001101000101000010110111 +
#132000
b11111111111111111111101010111100 $
b11111111111111111111101010111100 0
b11111111111111111111101010100001 "
b11111111111111111111101010100001 .
b11111111111111111111101010100000 %
b11111111111111111111101010100000 1
b10101011110011011110000000000000 !
b10101011110011011110000000000000 -
b11111111111111011110001010111100 #
b11111111111111011110001010111100 /
b10101011110011011110000010010111 '
b10101011110011011110000010010111 ,
b1100 *
b10101011110011011110000000000000 2
b10101011110011011110000010010111 4
b1010101001011010111010001111001011100000110010100100000011010010110110101101101001000000010100001000001010101010100100101010000010000110010100100100000001111010010000000110000011110000100000101000010010000110100010001000101001100000011000000110000 6
#134000
b1100 )
b10101011110011011110000000000000 3
b10111 5
b10101011110011011110000010010111 +
#144000
b100000 $
b100000 0
b100001 "
b100001 .
b100000100000 %
b100000100000 1
b10000000000000000000000000 !
b10000000000000000000000000 -
b100000 #
b100000 /
b10000000000000000011101111 '
b10000000000000000011101111 ,
b1101 *
b100000 2
b10000000000000000011101111 4
b10010100010110101110100011110010111000001100101001000000110100101101101011011010010000000111101001000000010101100110011001100100010000000101000011010100110000101101100001000000110011001101111011100100111011101100001011100100110010000101001 6
#146000
b1101 )
b100000 3
b1101111 5
b10000000000000000011101111 +
#156000
b11111111111111111111111111100001 $
b11111111111111111111111111100001 0
b11111111111111111111111111100001 "
b11111111111111111111111111100001 .
b11111111111111111111111111100000 %
b11111111111111111111111111100000 1
b11111110000111111111000000000000 !
b11111110000111111111000000000000 -
b11111111111111111111111111100000 #
b11111111111111111111111111100000 /
b11111110000111111111000011101111 '
b11111110000111111111000011101111 ,
b1110 *
b11111111111111111111111111100000 2
b11111110000111111111000011101111 4
b1001010001011010111010001111001011100000110010100100000011010010110110101101101001000000011110100100000001011010011001100110010001000000010100001101010011000010110110000100000011000100110000101100011011010110111011101100001011100100110010000101001 6
#158000
b1110 )
b11111111111111111111111111100000 3
b11111110000111111111000011101111 +
#168000
b11111111111111111111111111111111 $
b11111111111111111111111111111111 0
b11111111111111111111111111111111 "
b11111111111111111111111111111111 .
b11111111111111111111111111111110 %
b11111111111111111111111111111110 1
b11111111111111111111000000000000 !
b11111111111111111111000000000000 -
b11111111111111111111111111111110 #
b11111111111111111111111111111110 /
b11111111111111111111111111111111 '
b11111111111111111111111111111111 ,
b1111 *
b0 2
b11111111111111111111111111111111 4
b100010001100101011001100110000101110101011011000111010000100000011000110110000101110011011001010010000000101000011101010110111001101011011011100110111101110111011011100010000001101111011100000110001101101111011001000110010100101001001000000010110100111110001000000110100101101101011011010011110100110000 6
#170000
b1111 )
b0 3
b1111111 5
b11111111111111111111111111111111 +
