src/pc_next_logic.v
//=====================================================================
// File        : pc_next_logic.v
// Author      : Prabhat Pandey
// Created On  : 16-Feb-2026
// Project     : RV32I Single-Cycle 32-bit RISC-V Processor
// Module Name : pc_next_logic
// Description :
//   This module generates the next program counter (PC) value for an
//   RV32I single-cycle processor.
//
//   PC Update Sources (priority order):
//     1) JALR : pc_next = (rs1 + immI) & ~1
//     2) JAL  : pc_next = pc_current + immJ
//     3) BRANCH taken : pc_next = pc_current + immB
//     4) Default : pc_next = pc_current + 4
//
// Inputs:
//   - pc_current   : current PC
//   - rs1_val      : value of rs1 (needed for JALR target)
//   - imm_i        : I-type immediate (for JALR)
//   - imm_b        : B-type immediate (for branch target)
//   - imm_j        : J-type immediate (for JAL target)
//   - branch       : indicates instruction is a branch
//   - take_branch  : output from branch_unit (branch condition result)
//   - jump         : indicates JAL instruction
//   - jalr         : indicates JALR instruction
//
// Outputs:
//   - pc_next       : next PC
//   - pc_plus4      : pc_current + 4 (useful for writeback on jal/jalr)
//
// Notes:
//   - RISC-V spec requires JALR target to have bit0 = 0.
//     That is why we AND with 32'hFFFF_FFFE.
//   - This module does NOT check illegal combinations of control
//     signals. The controller must ensure only valid combinations.
//
// Revision History:
//   - 16-Feb-2026 : Initial version
//=====================================================================

module pc_next_logic (
    input  wire [31:0] pc_current,    // Current PC
    input  wire [31:0] rs1_val,       // rs1 value (for jalr)
    input  wire [31:0] imm_i,         // I-type immediate
    input  wire [31:0] imm_b,         // B-type immediate
    input  wire [31:0] imm_j,         // J-type immediate

    input  wire        branch,        // branch instruction
    input  wire        take_branch,   // branch condition result
    input  wire        jump,          // jal instruction
    input  wire        jalr,          // jalr instruction

    output reg  [31:0] pc_next,       // Next PC
    output wire [31:0] pc_plus4       // PC + 4
);

    //=================================================================
    // PC + 4 calculation
    //=================================================================
    assign pc_plus4 = pc_current + 32'd4;

    //=================================================================
    // Combinational PC next selection logic
    //=================================================================
    always @(*) begin

        // Default: sequential execution
        pc_next = pc_plus4;

        // Priority 1: JALR (highest priority)
        if (jalr) begin
            // Spec: clear bit0 of target address
            pc_next = (rs1_val + imm_i) & 32'hFFFF_FFFE;
        end

        // Priority 2: JAL
        else if (jump) begin
            pc_next = pc_current + imm_j;
        end

        // Priority 3: Branch taken
        else if (branch && take_branch) begin
            pc_next = pc_current + imm_b;
        end

        // Else: pc_next stays pc_plus4
    end

endmodule

RTL_Verification/tb_pc_next_logic.v
//=====================================================================
// File        : tb_pc_next_logic.v
// Author      : Prabhat Pandey
// Created On  : 16-Feb-2026
// Project     : RV32I Single-Cycle 32-bit RISC-V Processor
// Testbench   : tb_pc_next_logic
// Description :
//   Fully self-checking testbench for pc_next_logic.v
//
// PC Update Priority (must match DUT):
//   1) JALR : pc_next = (rs1 + imm_i) & ~1
//   2) JAL  : pc_next = pc_current + imm_j
//   3) BRANCH taken : pc_next = pc_current + imm_b
//   4) Default : pc_next = pc_current + 4
//
// Verification Features:
//   - Fully self-checking
//   - Input print per test
//   - Expected output print
//   - Actual output print
//   - PASS/FAIL per test
//   - Global counters
//   - Final verification summary report
//
// Run Commands:
//   iverilog -o ./Verification_Results/result_tb_pc_next_logic ./src/pc_next_logic.v ./RTL_Verification/tb_pc_next_logic.v
//   vvp ./Verification_Results/result_tb_pc_next_logic
//=====================================================================

`timescale 1ns/1ps

module tb_pc_next_logic;

    //=============================================================
    // Testbench Parameters
    //=============================================================
    localparam integer TEST_DELAY = 10; // ns between tests for waveform visibility

    //=============================================================
    // DUT Inputs
    //=============================================================
    reg  [31:0] pc_current;
    reg  [31:0] rs1_val;
    reg  [31:0] imm_i;
    reg  [31:0] imm_b;
    reg  [31:0] imm_j;

    reg         branch;
    reg         take_branch;
    reg         jump;
    reg         jalr;

    //=============================================================
    // DUT Outputs
    //=============================================================
    wire [31:0] pc_next;
    wire [31:0] pc_plus4;

    //=============================================================
    // Instantiate DUT
    //=============================================================
    pc_next_logic dut (
        .pc_current  (pc_current),
        .rs1_val     (rs1_val),
        .imm_i       (imm_i),
        .imm_b       (imm_b),
        .imm_j       (imm_j),
        .branch      (branch),
        .take_branch (take_branch),
        .jump        (jump),
        .jalr        (jalr),
        .pc_next     (pc_next),
        .pc_plus4    (pc_plus4)
    );

    //=============================================================
    // Global Counters
    //=============================================================
    integer total_tests;
    integer passed_tests;
    integer failed_tests;

    //=============================================================
    // VCD Dump (for GTKWave)
    //=============================================================
    initial begin
        $dumpfile("Verification_Results/vcd/tb_pc_next_logic.vcd");
        $dumpvars(0, tb_pc_next_logic);
    end

    //=============================================================
    // Task: Divider
    //=============================================================
    task print_divider;
        begin
            $display("----------------------------------------------------------------");
        end
    endtask

    //=============================================================
    // Task: Run One Test
    //=============================================================
    task run_test;
        input [8*70:1] test_name;

        input [31:0] pc_in;
        input [31:0] rs1_in;
        input [31:0] imm_i_in;
        input [31:0] imm_b_in;
        input [31:0] imm_j_in;

        input        branch_in;
        input        take_branch_in;
        input        jump_in;
        input        jalr_in;

        input [31:0] expected_pc_next;
        input [31:0] expected_pc_plus4;

        reg [31:0] got_pc_next;
        reg [31:0] got_pc_plus4;

        begin
            total_tests = total_tests + 1;

            print_divider();
            $display("TEST : %s", test_name);

            // Apply inputs
            pc_current  = pc_in;
            rs1_val     = rs1_in;
            imm_i       = imm_i_in;
            imm_b       = imm_b_in;
            imm_j       = imm_j_in;

            branch      = branch_in;
            take_branch = take_branch_in;
            jump        = jump_in;
            jalr        = jalr_in;

            #2; // settle combinational logic

            got_pc_next  = pc_next;
            got_pc_plus4 = pc_plus4;

            // Print Inputs
            $display("Inputs:");
            $display("   pc_current   = %08h", pc_in);
            $display("   rs1_val      = %08h", rs1_in);
            $display("   imm_i        = %08h", imm_i_in);
            $display("   imm_b        = %08h", imm_b_in);
            $display("   imm_j        = %08h", imm_j_in);
            $display("");
            $display("   branch       = %0d", branch_in);
            $display("   take_branch  = %0d", take_branch_in);
            $display("   jump         = %0d", jump_in);
            $display("   jalr         = %0d", jalr_in);

            // Print Expected
            $display("");
            $display("Expected:");
            $display("   pc_plus4     = %08h", expected_pc_plus4);
            $display("   pc_next      = %08h", expected_pc_next);

            // Print Got
            $display("");
            $display("Got:");
            $display("   pc_plus4     = %08h", got_pc_plus4);
            $display("   pc_next      = %08h", got_pc_next);

            // Compare
            if ((got_pc_next === expected_pc_next) &&
                (got_pc_plus4 === expected_pc_plus4)) begin
                passed_tests = passed_tests + 1;
                $display("STATUS: PASS");
            end
            else begin
                failed_tests = failed_tests + 1;
                $display("STATUS: FAIL");
            end

            print_divider();
            $display("");

            #(TEST_DELAY);
        end
    endtask

    //=============================================================
    // Main Test Sequence
    //=============================================================
    initial begin

        // Init counters
        total_tests  = 0;
        passed_tests = 0;
        failed_tests = 0;

        // Init signals
        pc_current   = 32'h0000_0000;
        rs1_val      = 32'h0000_0000;
        imm_i        = 32'h0000_0000;
        imm_b        = 32'h0000_0000;
        imm_j        = 32'h0000_0000;
        branch       = 1'b0;
        take_branch  = 1'b0;
        jump         = 1'b0;
        jalr         = 1'b0;

        $display("====================================================");
        $display(" PC_NEXT_LOGIC VERIFICATION STARTED — Author: Prabhat Pandey");
        $display("====================================================");
        $display("");

        //=========================================================
        // TEST 1: Default PC+4
        //=========================================================
        run_test("Default: no branch/jump -> PC+4",
                 32'h0000_0100,
                 32'h0000_0000,
                 32'h0000_0000,
                 32'h0000_0010,
                 32'h0000_0020,
                 1'b0, 1'b0, 1'b0, 1'b0,
                 32'h0000_0104,
                 32'h0000_0104);

        //=========================================================
        // TEST 2: Branch not taken -> PC+4
        //=========================================================
        run_test("Branch not taken -> PC+4",
                 32'h0000_0200,
                 32'h0000_0000,
                 32'h0000_0000,
                 32'h0000_0010,  // imm_b
                 32'h0000_0000,
                 1'b1, 1'b0, 1'b0, 1'b0,
                 32'h0000_0204,
                 32'h0000_0204);

        //=========================================================
        // TEST 3: Branch taken -> PC + imm_b
        //=========================================================
        run_test("Branch taken -> PC + imm_b",
                 32'h0000_0200,
                 32'h0000_0000,
                 32'h0000_0000,
                 32'h0000_0010,  // +16
                 32'h0000_0000,
                 1'b1, 1'b1, 1'b0, 1'b0,
                 32'h0000_0210,
                 32'h0000_0204);

        //=========================================================
        // TEST 4: JAL -> PC + imm_j
        //=========================================================
        run_test("JAL -> PC + imm_j",
                 32'h0000_0300,
                 32'h0000_0000,
                 32'h0000_0000,
                 32'h0000_0040,
                 32'h0000_0020,  // +32
                 1'b0, 1'b0, 1'b1, 1'b0,
                 32'h0000_0320,
                 32'h0000_0304);

        //=========================================================
        // TEST 5: JALR -> (rs1 + imm_i) & ~1 (bit0 cleared)
        //=========================================================
        // rs1=0x1003, imm_i=0x00000004 => target=0x1007
        // bit0 cleared => 0x1006
        run_test("JALR -> (rs1+imm_i)&~1 (bit0 cleared)",
                 32'h0000_0000,
                 32'h0000_1003,
                 32'h0000_0004,
                 32'h0000_0000,
                 32'h0000_0000,
                 1'b0, 1'b0, 1'b0, 1'b1,
                 32'h0000_1006,
                 32'h0000_0004);

        //=========================================================
        // TEST 6: Priority check: JALR overrides JAL
        //=========================================================
        run_test("Priority: JALR overrides JAL",
                 32'h0000_0400,
                 32'h0000_2000,
                 32'h0000_0008,  // rs1+imm_i = 0x2008 -> already aligned
                 32'h0000_0100,
                 32'h0000_0200,
                 1'b0, 1'b0, 1'b1, 1'b1,
                 32'h0000_2008,
                 32'h0000_0404);

        //=========================================================
        // TEST 7: Priority check: JAL overrides Branch
        //=========================================================
        run_test("Priority: JAL overrides taken Branch",
                 32'h0000_0500,
                 32'h0000_0000,
                 32'h0000_0000,
                 32'h0000_0010,  // branch target
                 32'h0000_0040,  // jal target
                 1'b1, 1'b1, 1'b1, 1'b0,
                 32'h0000_0540,
                 32'h0000_0504);

        //=========================================================
        // TEST 8: Branch taken overrides PC+4
        //=========================================================
        run_test("Branch taken overrides PC+4",
                 32'h0000_0600,
                 32'h0000_0000,
                 32'h0000_0000,
                 32'hFFFF_FFF0,  // -16
                 32'h0000_0000,
                 1'b1, 1'b1, 1'b0, 1'b0,
                 32'h0000_05F0,
                 32'h0000_0604);

        //=========================================================
        // Final Summary Report
        //=========================================================
        $display("====================================================");
        $display(" PC_NEXT_LOGIC VERIFICATION REPORT");
        $display("====================================================");
        $display("   Total Tests   : %0d", total_tests);
        $display("   Passed        : %0d", passed_tests);
        $display("   Failed        : %0d", failed_tests);
        $display("====================================================");

        if (failed_tests == 0) begin
            $display("STATUS: ALL TESTS PASSED");
        end
        else begin
            $display("STATUS: SOME TESTS FAILED");
        end

        $display("====================================================");
        $display("");

        $finish;
    end

endmodule

Verification_Results/vcd/tb_pc_next_logic.vcd
$date
	Mon Mar  9 20:55:09 2026
$end
$version
	Icarus Verilog
$end
$timescale
	1ps
$end
$scope module tb_pc_next_logic $end
$var wire 32 ! pc_plus4 [31:0] $end
$var wire 32 " pc_next [31:0] $end
$var parameter 32 # TEST_DELAY $end
$var reg 1 $ branch $end
$var reg 32 % imm_b [31:0] $end
$var reg 32 & imm_i [31:0] $end
$var reg 32 ' imm_j [31:0] $end
$var reg 1 ( jalr $end
$var reg 1 ) jump $end
$var reg 32 * pc_current [31:0] $end
$var reg 32 + rs1_val [31:0] $end
$var reg 1 , take_branch $end
$var integer 32 - failed_tests [31:0] $end
$var integer 32 . passed_tests [31:0] $end
$var integer 32 / total_tests [31:0] $end
$scope module dut $end
$var wire 1 $ branch $end
$var wire 32 0 imm_b [31:0] $end
$var wire 32 1 imm_i [31:0] $end
$var wire 32 2 imm_j [31:0] $end
$var wire 1 ( jalr $end
$var wire 1 ) jump $end
$var wire 32 3 pc_current [31:0] $end
$var wire 32 4 rs1_val [31:0] $end
$var wire 1 , take_branch $end
$var wire 32 5 pc_plus4 [31:0] $end
$var reg 32 6 pc_next [31:0] $end
$upscope $end
$scope task print_divider $end
$upscope $end
$scope task run_test $end
$var reg 1 7 branch_in $end
$var reg 32 8 expected_pc_next [31:0] $end
$var reg 32 9 expected_pc_plus4 [31:0] $end
$var reg 32 : got_pc_next [31:0] $end
$var reg 32 ; got_pc_plus4 [31:0] $end
$var reg 32 < imm_b_in [31:0] $end
$var reg 32 = imm_i_in [31:0] $end
$var reg 32 > imm_j_in [31:0] $end
$var reg 1 ? jalr_in $end
$var reg 1 @ jump_in $end
$var reg 32 A pc_in [31:0] $end
$var reg 32 B rs1_in [31:0] $end
$var reg 1 C take_branch_in $end
$var reg 560 D test_name [560:1] $end
$upscope $end
$upscope $end
$enddefinitions $end
$comment Show the parameter values. $end
$dumpall
b1010 #
$end
#0
$dumpvars
b1000100011001010110011001100001011101010110110001110100001110100010000001101110011011110010000001100010011100100110000101101110011000110110100000101111011010100111010101101101011100000010000000101101001111100010000001010000010000110010101100110100 D
0C
b0 B
b100000000 A
0@
0?
b100000 >
b0 =
b10000 <
bx ;
bx :
b100000100 9
b100000100 8
07
b100000100 6
b100000100 5
b0 4
b100000000 3
b100000 2
b0 1
b10000 0
b1 /
b0 .
b0 -
0,
b0 +
b100000000 *
0)
0(
b100000 '
b0 &
b10000 %
0$
b100000100 "
b100000100 !
$end
#2000
b1 .
b100000100 ;
b100000100 :
#12000
b1000000100 "
b1000000100 6
1$
b0 '
b0 2
b1000000100 !
b1000000100 5
b1000000000 *
b1000000000 3
b10 /
b1000000100 9
b1000000100 8
17
b0 >
b1000000000 A
b10000100111001001100001011011100110001101101000001000000110111001101111011101000010000001110100011000010110101101100101011011100010000000101101001111100010000001010000010000110010101100110100 D
#14000
b10 .
b1000000100 ;
b1000000100 :
#24000
b1000010000 "
b1000010000 6
1,
b11 /
b1000010000 8
1C
b100001001110010011000010110111001100011011010000010000001110100011000010110101101100101011011100010000000101101001111100010000001010000010000110010000000101011001000000110100101101101011011010101111101100010 D
#26000
b11 .
b1000010000 :
#36000
b1100100000 "
b1100100000 6
1)
0,
0$
b100000 '
b100000 2
b1000000 %
b1000000 0
b1100000100 !
b1100000100 5
b1100000000 *
b1100000000 3
b100 /
b1100000100 9
b1100100000 8
1@
0C
07
b100000 >
b1000000 <
b1100000000 A
b100101001000001010011000010000000101101001111100010000001010000010000110010000000101011001000000110100101101101011011010101111101101010 D
#38000
b100 .
b1100000100 ;
b1100100000 :
#48000
b1000000000110 "
b1000000000110 6
1(
0)
b0 '
b0 2
b0 %
b0 0
b100 &
b100 1
b1000000000011 +
b1000000000011 4
b100 !
b100 5
b0 *
b0 3
b101 /
b100 9
b1000000000110 8
1?
0@
b0 >
b0 <
b100 =
b1000000000011 B
b0 A
b1001010010000010100110001010010001000000010110100111110001000000010100001110010011100110011000100101011011010010110110101101101010111110110100100101001001001100111111000110001001000000010100001100010011010010111010000110000001000000110001101101100011001010110000101110010011001010110010000101001 D
#50000
b101 .
b100 ;
b1000000000110 :
#60000
b10000000001000 "
b10000000001000 6
1)
b1000000000 '
b1000000000 2
b100000000 %
b100000000 0
b1000 &
b1000 1
b10000000000000 +
b10000000000000 4
b10000000100 !
b10000000100 5
b10000000000 *
b10000000000 3
b110 /
b10000000100 9
b10000000001000 8
1@
b1000000000 >
b100000000 <
b1000 =
b10000000000000 B
b10000000000 A
b1010000011100100110100101101111011100100110100101110100011110010011101000100000010010100100000101001100010100100010000001101111011101100110010101110010011100100110100101100100011001010111001100100000010010100100000101001100 D
#62000
b110 .
b10000000100 ;
b10000000001000 :
#72000
b10101000000 "
b10101000000 6
0(
1,
1$
b1000000 '
b1000000 2
b10000 %
b10000 0
b0 &
b0 1
b0 +
b0 4
b10100000100 !
b10100000100 5
b10100000000 *
b10100000000 3
b111 /
b10100000100 9
b10101000000 8
0?
1C
17
b1000000 >
b10000 <
b0 =
b0 B
b10100000000 A
b10100000111001001101001011011110111001001101001011101000111100100111010001000000100101001000001010011000010000001101111011101100110010101110010011100100110100101100100011001010111001100100000011101000110000101101011011001010110111000100000010000100111001001100001011011100110001101101000 D
#74000
b111 .
b10100000100 ;
b10101000000 :
#84000
b10111110000 "
b10111110000 6
0)
b0 '
b0 2
b11111111111111111111111111110000 %
b11111111111111111111111111110000 0
b11000000100 !
b11000000100 5
b11000000000 *
b11000000000 3
b1000 /
b11000000100 9
b10111110000 8
0@
b0 >
b11111111111111111111111111110000 <
b11000000000 A
b10000100111001001100001011011100110001101101000001000000111010001100001011010110110010101101110001000000110111101110110011001010111001001110010011010010110010001100101011100110010000001010000010000110010101100110100 D
#86000
b1000 .
b11000000100 ;
b10111110000 :
