src/regfile.v
//=====================================================================
// File        : regfile.v
// Author      : Prabhat Pandey
// Created On  : 13-Feb-2026
// Project     : RV32I Single-Cycle 32-bit RISC-V Processor
// Module Name : regfile
// Description :
//   This module implements a 32x32 Register File for RV32I.
//
// Features:
//   - 32 registers (x0 to x31), each 32-bit wide
//   - 2 read ports (combinational)
//   - 1 write port (synchronous on posedge clk)
//   - Active-low reset (rst_n)
//   - x0 is hardwired to 0 (writes to x0 are ignored)
//
// Inputs:
//   - clk   : clock
//   - rst_n : active-low reset
//   - we    : write enable
//   - rs1   : source register 1 index
//   - rs2   : source register 2 index
//   - rd    : destination register index
//   - wd    : write data
//
// Outputs:
//   - rd1   : data from rs1
//   - rd2   : data from rs2
//
// Notes:
//   - Reads are asynchronous (combinational).
//   - Writes happen only on rising edge of clk.
//   - On reset, all registers become 0.
//
// Revision History:
//   - 16-Feb-2026 : Added rst_n support + reset clearing.
//   - 13-Feb-2026 : Initial version
//=====================================================================

module regfile (
    input  wire        clk,      // Clock input (positive-edge triggered)
    input  wire        rst_n,    // Active-low reset
    input  wire        we,       // Write enable
    input  wire [4:0]  rs1,      // Source register 1 index
    input  wire [4:0]  rs2,      // Source register 2 index
    input  wire [4:0]  rd,       // Destination register index
    input  wire [31:0] wd,       // Write data
    output wire [31:0] rd1,      // Read data from rs1
    output wire [31:0] rd2       // Read data from rs2
);

    //=============================================================
    // Register array: x0..x31
    //=============================================================
    reg [31:0] regs [0:31];

    integer i;

    //=============================================================
    // Synchronous write + reset logic
    //=============================================================
    always @(posedge clk) begin
        if (!rst_n) begin
            // Reset: clear all registers
            for (i = 0; i < 32; i = i + 1)
                regs[i] <= 32'h0000_0000;
        end
        else begin
            // Normal write (ignore writes to x0)
            if (we && (rd != 5'd0))
                regs[rd] <= wd;

            // Force x0 = 0 always (extra safety)
            regs[0] <= 32'h0000_0000;
        end
    end

    //=============================================================
    // Combinational read ports
    //=============================================================
    assign rd1 = (rs1 == 5'd0) ? 32'h0000_0000 : regs[rs1];
    assign rd2 = (rs2 == 5'd0) ? 32'h0000_0000 : regs[rs2];

endmodule

RTL_Verification/tb_regfile.v
//=====================================================================
// File        : tb_regfile.v
// Author      : Prabhat Pandey
// Created On  : 16-Feb-2026
// Project     : RV32I Single-Cycle 32-bit RISC-V Processor
// Testbench   : tb_regfile
// Description :
//   Fully self-checking testbench for regfile.v (32x32 register file)
//
// Verified Features:
//   1) Reset clears all registers to 0 (rst_n active-low)
//   2) Writes happen on posedge clk when we=1
//   3) Reads are combinational (async)
//   4) Writes to x0 are ignored
//   5) x0 always reads as 0
//   6) Multiple registers store independent values
//
// Verification Features:
//   - Fully self-checking
//   - Input print per test
//   - Expected output print
//   - Actual output print
//   - PASS/FAIL per test
//   - Global counters
//   - Final verification summary report
//
// Run Commands:
//   iverilog -o ./Verification_Results/result_tb_regfile ./src/regfile.v ./RTL_Verification/tb_regfile.v
//   vvp ./Verification_Results/result_tb_regfile
//=====================================================================

`timescale 1ns/1ps

module tb_regfile;

    //=============================================================
    // Testbench Parameters
    //=============================================================
    localparam integer TEST_DELAY = 10; // ns between tests for waveform visibility

    //=============================================================
    // DUT Signals
    //=============================================================
    reg         clk;
    reg         rst_n;
    reg         we;
    reg  [4:0]  rs1;
    reg  [4:0]  rs2;
    reg  [4:0]  rd;
    reg  [31:0] wd;
    wire [31:0] rd1;
    wire [31:0] rd2;

    //=============================================================
    // Instantiate DUT
    //=============================================================
    regfile dut (
        .clk   (clk),
        .rst_n (rst_n),
        .we    (we),
        .rs1   (rs1),
        .rs2   (rs2),
        .rd    (rd),
        .wd    (wd),
        .rd1   (rd1),
        .rd2   (rd2)
    );

    //=============================================================
    // Global Counters
    //=============================================================
    integer total_tests;
    integer passed_tests;
    integer failed_tests;

    //=============================================================
    // VCD Dump (for GTKWave)
    //=============================================================
    initial begin
        $dumpfile("Verification_Results/vcd/tb_regfile.vcd");
        $dumpvars(0, tb_regfile);
    end

    //=============================================================
    // Clock Generation (10ns period)
    //=============================================================
    initial begin
        clk = 1'b0;
        forever #5 clk = ~clk;
    end

    //=============================================================
    // Task: Divider
    //=============================================================
    task print_divider;
        begin
            $display("----------------------------------------------------------------");
        end
    endtask

    //=============================================================
    // Task: Print inputs (common format)
    //=============================================================
    task print_inputs;
        input [4:0]  rs1_in;
        input [4:0]  rs2_in;
        input        we_in;
        input [4:0]  rd_in;
        input [31:0] wd_in;
        input        rst_n_in;
        begin
            $display("Inputs:");
            $display("   rst_n = %0d", rst_n_in);
            $display("   we    = %0d", we_in);
            $display("   rs1   = x%0d", rs1_in);
            $display("   rs2   = x%0d", rs2_in);
            $display("   rd    = x%0d", rd_in);
            $display("   wd    = %08h", wd_in);
        end
    endtask

    //=============================================================
    // Task: Run one read check
    //=============================================================
    task check_read;
        input [8*70:1] test_name;
        input [4:0]    rs1_in;
        input [4:0]    rs2_in;
        input [31:0]   exp_rd1;
        input [31:0]   exp_rd2;

        reg [31:0] got1;
        reg [31:0] got2;
        begin
            total_tests = total_tests + 1;

            print_divider();
            $display("TEST : %s", test_name);

            // Apply read addresses
            rs1 = rs1_in;
            rs2 = rs2_in;
            #2; // combinational settle

            got1 = rd1;
            got2 = rd2;

            print_inputs(rs1_in, rs2_in, we, rd, wd, rst_n);

            $display("");
            $display("Expected:");
            $display("   rd1   = %08h", exp_rd1);
            $display("   rd2   = %08h", exp_rd2);

            $display("");
            $display("Got:");
            $display("   rd1   = %08h", got1);
            $display("   rd2   = %08h", got2);

            if ((got1 === exp_rd1) && (got2 === exp_rd2)) begin
                passed_tests = passed_tests + 1;
                $display("STATUS: PASS");
            end
            else begin
                failed_tests = failed_tests + 1;
                $display("STATUS: FAIL");
            end

            print_divider();
            $display("");

            #(TEST_DELAY);
        end
   endtask

    //=============================================================
    // Task: Perform one write
    //=============================================================
    task do_write;
        input [8*70:1] step_name;
        input [4:0]    rd_in;
        input [31:0]   wd_in;
        input          we_in;

        begin
            print_divider();
            $display("STEP : %s", step_name);

            we = we_in;
            rd = rd_in;
            wd = wd_in;

            $display("Write Inputs:");
            $display("   we = %0d | rd = x%0d | wd = %08h", we_in, rd_in, wd_in);

            // Write happens on posedge
            @(posedge clk);
            #1;

            print_divider();
            $display("");

            #(TEST_DELAY);
        end
    endtask

    //=============================================================
    // Main Test Sequence
    //=============================================================
    initial begin

        // Init counters
        total_tests  = 0;
        passed_tests = 0;
        failed_tests = 0;

        // Init signals
        rst_n = 1'b0;
        we    = 1'b0;
        rs1   = 5'd0;
        rs2   = 5'd0;
        rd    = 5'd0;
        wd    = 32'h0000_0000;

        $display("====================================================");
        $display(" REGFILE VERIFICATION STARTED — Author: Prabhat Pandey");
        $display("====================================================");
        $display("");

        //=========================================================
        // TEST 1: Reset clears registers
        //=========================================================
        // Hold reset for 2 cycles
        @(posedge clk);
        @(posedge clk);
        #1;

        // Release reset
        rst_n = 1'b1;
        #2;

        // After reset release, check some registers are 0
        check_read("After reset: x0=0, x1=0",
                   5'd0, 5'd1,
                   32'h0000_0000, 32'h0000_0000);

        check_read("After reset: x10=0, x31=0",
                   5'd10, 5'd31,
                   32'h0000_0000, 32'h0000_0000);

        //=========================================================
        // TEST 2: Write to x1 and read back
        //=========================================================
        do_write("Write 0x11111111 into x1",
                 5'd1, 32'h1111_1111, 1'b1);

        check_read("Read back x1 should be 0x11111111",
                   5'd1, 5'd0,
                   32'h1111_1111, 32'h0000_0000);

        //=========================================================
        // TEST 3: Write to x2 and x3, verify independent
        //=========================================================
        do_write("Write 0x22222222 into x2",
                 5'd2, 32'h2222_2222, 1'b1);

        do_write("Write 0x33333333 into x3",
                 5'd3, 32'h3333_3333, 1'b1);

        check_read("Read x2 and x3 should match",
                   5'd2, 5'd3,
                   32'h2222_2222, 32'h3333_3333);

        //=========================================================
        // TEST 4: Write enable = 0 must not write
        //=========================================================
        do_write("Attempt write into x4 with we=0 (should NOT update)",
                 5'd4, 32'h4444_4444, 1'b0);

        check_read("x4 should still be 0",
                   5'd4, 5'd0,
                   32'h0000_0000, 32'h0000_0000);

        //=========================================================
        // TEST 5: Writes to x0 must be ignored
        //=========================================================
        do_write("Attempt write into x0 (must be ignored)",
                 5'd0, 32'hDEAD_BEEF, 1'b1);

        check_read("x0 must remain 0 always",
                   5'd0, 5'd1,
                   32'h0000_0000, 32'h1111_1111);

        //=========================================================
        // TEST 6: Reset again clears everything
        //=========================================================
        print_divider();
        $display("STEP : Apply reset again (rst_n=0)");
        rst_n = 1'b0;
        @(posedge clk);
        @(posedge clk);
        #1;
        rst_n = 1'b1;
        #2;
        print_divider();
        $display("");

        check_read("After 2nd reset: x1=0, x2=0",
                   5'd1, 5'd2,
                   32'h0000_0000, 32'h0000_0000);

        check_read("After 2nd reset: x3=0, x0=0",
                   5'd3, 5'd0,
                   32'h0000_0000, 32'h0000_0000);

        //=========================================================
        // Final Summary Report
        //=========================================================
        $display("====================================================");
        $display(" REGFILE VERIFICATION REPORT");
        $display("====================================================");
        $display("   Total Tests   : %0d", total_tests);
        $display("   Passed        : %0d", passed_tests);
        $display("   Failed        : %0d", failed_tests);
        $display("====================================================");

        if (failed_tests == 0) begin
            $display("STATUS: ALL TESTS PASSED");
        end
        else begin
            $display("STATUS: SOME TESTS FAILED");
        end

        $display("====================================================");
        $display("");

        $finish;
    end

endmodule

Verification_Results/vcd/tb_regfile.vcd
$date
	Mon Mar  9 23:42:22 2026
$end
$version
	Icarus Verilog
$end
$timescale
	1ps
$end
$scope module tb_regfile $end
$var wire 32 ! rd2 [31:0] $end
$var wire 32 " rd1 [31:0] $end
$var parameter 32 # TEST_DELAY $end
$var reg 1 $ clk $end
$var reg 5 % rd [4:0] $end
$var reg 5 & rs1 [4:0] $end
$var reg 5 ' rs2 [4:0] $end
$var reg 1 ( rst_n $end
$var reg 32 ) wd [31:0] $end
$var reg 1 * we $end
$var integer 32 + failed_tests [31:0] $end
$var integer 32 , passed_tests [31:0] $end
$var integer 32 - total_tests [31:0] $end
$scope module dut $end
$var wire 1 $ clk $end
$var wire 5 . rd [4:0] $end
$var wire 5 / rs1 [4:0] $end
$var wire 5 0 rs2 [4:0] $end
$var wire 1 ( rst_n $end
$var wire 32 1 wd [31:0] $end
$var wire 1 * we $end
$var wire 32 2 rd2 [31:0] $end
$var wire 32 3 rd1 [31:0] $end
$var integer 32 4 i [31:0] $end
$upscope $end
$scope task check_read $end
$var reg 32 5 exp_rd1 [31:0] $end
$var reg 32 6 exp_rd2 [31:0] $end
$var reg 32 7 got1 [31:0] $end
$var reg 32 8 got2 [31:0] $end
$var reg 5 9 rs1_in [4:0] $end
$var reg 5 : rs2_in [4:0] $end
$var reg 560 ; test_name [560:1] $end
$upscope $end
$scope task do_write $end
$var reg 5 < rd_in [4:0] $end
$var reg 560 = step_name [560:1] $end
$var reg 32 > wd_in [31:0] $end
$var reg 1 ? we_in $end
$upscope $end
$scope task print_divider $end
$upscope $end
$scope task print_inputs $end
$var reg 5 @ rd_in [4:0] $end
$var reg 5 A rs1_in [4:0] $end
$var reg 5 B rs2_in [4:0] $end
$var reg 1 C rst_n_in $end
$var reg 32 D wd_in [31:0] $end
$var reg 1 E we_in $end
$upscope $end
$upscope $end
$enddefinitions $end
$comment Show the parameter values. $end
$dumpall
b1010 #
$end
#0
$dumpvars
xE
bx D
xC
bx B
bx A
bx @
x?
bx >
bx =
bx <
bx ;
bx :
bx 9
bx 8
bx 7
bx 6
bx 5
bx 4
b0 3
b0 2
b0 1
b0 0
b0 /
b0 .
b0 -
b0 ,
b0 +
0*
b0 )
0(
b0 '
b0 &
b0 %
0$
b0 "
b0 !
$end
#5000
b100000 4
1$
#10000
0$
#15000
b100000 4
1$
#16000
1(
#18000
b1 '
b1 0
b1 -
b0 6
b0 5
b1 :
b0 9
b100000101100110011101000110010101110010001000000111001001100101011100110110010101110100001110100010000001111000001100000011110100110000001011000010000001111000001100010011110100110000 ;
#20000
b1 ,
1C
b0 D
b0 @
0E
b1 B
b0 A
b0 8
b0 7
0$
#25000
1$
#30000
0$
b11111 '
b11111 0
b1010 &
b1010 /
b10 -
b11111 :
b1010 9
b1000001011001100111010001100101011100100010000001110010011001010111001101100101011101000011101000100000011110000011000100110000001111010011000000101100001000000111100000110011001100010011110100110000 ;
#32000
b10 ,
b11111 B
b1010 A
#35000
1$
#40000
0$
#42000
b10001000100010001000100010001 )
b10001000100010001000100010001 1
b1 %
b1 .
1*
1?
b10001000100010001000100010001 >
b1 <
b10101110111001001101001011101000110010100100000001100000111100000110001001100010011000100110001001100010011000100110001001100010010000001101001011011100111010001101111001000000111100000110001 =
#45000
1$
#50000
0$
#55000
1$
#56000
b10001000100010001000100010001 "
b10001000100010001000100010001 3
b0 '
b0 0
b1 &
b1 /
b11 -
b10001000100010001000100010001 5
b0 :
b1 9
b10100100110010101100001011001000010000001100010011000010110001101101011001000000111100000110001001000000111001101101000011011110111010101101100011001000010000001100010011001010010000000110000011110000011000100110001001100010011000100110001001100010011000100110001 ;
#58000
b11 ,
b10001000100010001000100010001 D
b1 @
1E
b0 B
b1 A
b10001000100010001000100010001 7
#60000
0$
#65000
1$
#68000
b100010001000100010001000100010 )
b100010001000100010001000100010 1
b10 %
b10 .
b100010001000100010001000100010 >
b10 <
b10101110111001001101001011101000110010100100000001100000111100000110010001100100011001000110010001100100011001000110010001100100010000001101001011011100111010001101111001000000111100000110010 =
#70000
0$
#75000
1$
#80000
0$
#85000
1$
#86000
b110011001100110011001100110011 )
b110011001100110011001100110011 1
b11 %
b11 .
b110011001100110011001100110011 >
b11 <
b10101110111001001101001011101000110010100100000001100000111100000110011001100110011001100110011001100110011001100110011001100110010000001101001011011100111010001101111001000000111100000110011 =
#90000
0$
#95000
1$
#100000
0$
#105000
1$
#106000
b110011001100110011001100110011 !
b110011001100110011001100110011 2
b100010001000100010001000100010 "
b100010001000100010001000100010 3
b11 '
b11 0
b10 &
b10 /
b100 -
b110011001100110011001100110011 6
b100010001000100010001000100010 5
b11 :
b10 9
b10100100110010101100001011001000010000001111000001100100010000001100001011011100110010000100000011110000011001100100000011100110110100001101111011101010110110001100100001000000110110101100001011101000110001101101000 ;
#108000
b100 ,
b110011001100110011001100110011 D
b11 @
b11 B
b10 A
b110011001100110011001100110011 8
b100010001000100010001000100010 7
#110000
0$
#115000
1$
#118000
b1000100010001000100010001000100 )
b1000100010001000100010001000100 1
b100 %
b100 .
0*
0?
b1000100010001000100010001000100 >
b100 <
b10000010111010001110100011001010110110101110000011101000010000001110111011100100110100101110100011001010010000001101001011011100111010001101111001000000111100000110100001000000111011101101001011101000110100000100000011101110110010100111101001100000010000000101000011100110110100001101111011101010110110001100100001000000100111001001111010101000010000001110101011100000110010001100001011101000110010100101001 =
#120000
0$
#125000
1$
#130000
0$
#135000
1$
#136000
b0 !
b0 2
b0 "
b0 3
b0 '
b0 0
b100 &
b100 /
b101 -
b0 6
b0 5
b0 :
b100 9
b111100000110100001000000111001101101000011011110111010101101100011001000010000001110011011101000110100101101100011011000010000001100010011001010010000000110000 ;
#138000
b101 ,
b1000100010001000100010001000100 D
b100 @
0E
b0 B
b100 A
b0 8
b0 7
#140000
0$
#145000
1$
#148000
b11011110101011011011111011101111 )
b11011110101011011011111011101111 1
b0 %
b0 .
1*
1?
b11011110101011011011111011101111 >
b0 <
b10000010111010001110100011001010110110101110000011101000010000001110111011100100110100101110100011001010010000001101001011011100111010001101111001000000111100000110000001000000010100001101101011101010111001101110100001000000110001001100101001000000110100101100111011011100110111101110010011001010110010000101001 =
#150000
0$
#155000
1$
#160000
0$
#165000
1$
#166000
b10001000100010001000100010001 !
b10001000100010001000100010001 2
b1 '
b1 0
b0 &
b0 /
b110 -
b10001000100010001000100010001 6
b1 :
b0 9
b111100000110000001000000110110101110101011100110111010000100000011100100110010101101101011000010110100101101110001000000011000000100000011000010110110001110111011000010111100101110011 ;
#168000
b110 ,
b11011110101011011011111011101111 D
b0 @
1E
b1 B
b0 A
b10001000100010001000100010001 8
#170000
0$
#175000
1$
#178000
0(
#180000
0$
#185000
b0 !
b0 2
b100000 4
1$
#190000
0$
#195000
b100000 4
1$
#196000
1(
#198000
b10 '
b10 0
b1 &
b1 /
b111 -
b0 6
b10 :
b1 9
b10000010110011001110100011001010111001000100000001100100110111001100100001000000111001001100101011100110110010101110100001110100010000001111000001100010011110100110000001011000010000001111000001100100011110100110000 ;
#200000
b111 ,
b10 B
b1 A
b0 8
0$
#205000
1$
#210000
0$
b0 '
b0 0
b11 &
b11 /
b1000 -
b0 :
b11 9
b10000010110011001110100011001010111001000100000001100100110111001100100001000000111001001100101011100110110010101110100001110100010000001111000001100110011110100110000001011000010000001111000001100000011110100110000 ;
#212000
b1000 ,
b0 B
b11 A
