src/wb_mux.v
//=====================================================================
// File        : wb_mux.v
// Author      : Prabhat Pandey
// Created On  : 16-Feb-2026
// Project     : RV32I Single-Cycle 32-bit RISC-V Processor
// Module Name : wb_mux
// Description :
//   This module implements the Writeback Multiplexer for an RV32I
//   single-cycle processor.
//
//   The writeback mux selects which value is written back into the
//   destination register (rd) of the register file.
//
// Inputs:
//   - wb_sel      : 3-bit writeback select (from controller)
//   - alu_result  : result from ALU (R-type, I-type, address calc)
//   - mem_data    : data loaded from data memory (lw)
//   - pc_plus4    : PC + 4 (jal/jalr link address)
//   - u_imm       : U-type immediate (lui) -> imm[31:12] << 12
//   - pc_plus_imm : PC + immediate (auipc)
//
// Output:
//   - wb_data     : final data written into regfile
//
// wb_sel Encoding:
//   000 : ALU result
//   001 : Memory read data
//   010 : PC + 4
//   011 : U-immediate (LUI)
//   100 : PC + immediate (AUIPC)
//   others : 0 (safe)
//
// Notes:
//   - This module is purely combinational.
//   - A safe default of 0 is used for unused wb_sel values.
//
// Revision History:
//   - 16-Feb-2026 : Initial version
//=====================================================================

module wb_mux (
    input  wire [2:0]  wb_sel,       // writeback select
    input  wire [31:0] alu_result,   // from ALU
    input  wire [31:0] mem_data,     // from DMEM (lw)
    input  wire [31:0] pc_plus4,     // PC + 4
    input  wire [31:0] u_imm,        // LUI immediate
    input  wire [31:0] pc_plus_imm,  // AUIPC result
    output reg  [31:0] wb_data       // final writeback data
);

    //=================================================================
    // Combinational Writeback Selection
    //=================================================================
    always @(*) begin
        case (wb_sel)

            3'b000: wb_data = alu_result;   // ALU result
            3'b001: wb_data = mem_data;     // Load data
            3'b010: wb_data = pc_plus4;     // Link address (JAL/JALR)
            3'b011: wb_data = u_imm;        // LUI
            3'b100: wb_data = pc_plus_imm;  // AUIPC

            default: wb_data = 32'h0000_0000; // safe

        endcase
    end

endmodule

RTL_Verification/tb_wb_mux.v
//=====================================================================
// File        : tb_wb_mux.v
// Author      : Prabhat Pandey
// Created On  : 16-Feb-2026
// Project     : RV32I Single-Cycle 32-bit RISC-V Processor
// Testbench   : tb_wb_mux
// Description :
//   Fully self-checking testbench for wb_mux.v
//
// wb_sel Encoding:
//   000 : ALU result
//   001 : Memory read data
//   010 : PC + 4
//   011 : U-immediate (LUI)
//   100 : PC + immediate (AUIPC)
//   others : 0 (safe)
//
// Verification Features:
//   - Fully self-checking
//   - Input print per test
//   - Expected output print
//   - Actual output print
//   - PASS/FAIL per test case
//   - Global counters
//   - Final verification summary report
//
// Run Commands:
//   iverilog -o ./Verification_Results/result_tb_wb_mux ./src/wb_mux.v ./RTL_Verification/tb_wb_mux.v
//   vvp ./Verification_Results/result_tb_wb_mux
//=====================================================================

`timescale 1ns/1ps

module tb_wb_mux;

    //=============================================================
    // Testbench Parameters
    //=============================================================
    localparam integer TEST_DELAY = 10; // ns between tests for waveform visibility

    //=============================================================
    // DUT Inputs
    //=============================================================
    reg  [2:0]  wb_sel;
    reg  [31:0] alu_result;
    reg  [31:0] mem_data;
    reg  [31:0] pc_plus4;
    reg  [31:0] u_imm;
    reg  [31:0] pc_plus_imm;

    //=============================================================
    // DUT Output
    //=============================================================
    wire [31:0] wb_data;

    //=============================================================
    // Instantiate DUT
    //=============================================================
    wb_mux dut (
        .wb_sel      (wb_sel),
        .alu_result  (alu_result),
        .mem_data    (mem_data),
        .pc_plus4    (pc_plus4),
        .u_imm       (u_imm),
        .pc_plus_imm (pc_plus_imm),
        .wb_data     (wb_data)
    );

    //=============================================================
    // Global Counters
    //=============================================================
    integer total_tests;
    integer passed_tests;
    integer failed_tests;

    //=============================================================
    // VCD Dump (for GTKWave)
    //=============================================================
    initial begin
        $dumpfile("Verification_Results/vcd/tb_wb_mux.vcd");
        $dumpvars(0, tb_wb_mux);
    end

    //=============================================================
    // Task: Divider
    //=============================================================
    task print_divider;
        begin
            $display("----------------------------------------------------------------");
        end
    endtask

    //=============================================================
    // Task: Run One Test
    //=============================================================
    task run_test;
        input [8*70:1] test_name;

        input [2:0]  wb_sel_in;
        input [31:0] alu_in;
        input [31:0] mem_in;
        input [31:0] pc4_in;
        input [31:0] uimm_in;
        input [31:0] pcimm_in;

        input [31:0] expected_wb;

        reg [31:0] got_wb;
        begin
            total_tests = total_tests + 1;

            print_divider();
            $display("TEST : %s", test_name);

            // Apply inputs
            wb_sel      = wb_sel_in;
            alu_result  = alu_in;
            mem_data    = mem_in;
            pc_plus4    = pc4_in;
            u_imm       = uimm_in;
            pc_plus_imm = pcimm_in;

            #2; // settle

            got_wb = wb_data;

            // Print Inputs
            $display("Inputs:");
            $display("   wb_sel      = %03b", wb_sel_in);
            $display("   alu_result  = %08h", alu_in);
            $display("   mem_data    = %08h", mem_in);
            $display("   pc_plus4    = %08h", pc4_in);
            $display("   u_imm       = %08h", uimm_in);
            $display("   pc_plus_imm = %08h", pcimm_in);

            // Print Expected
            $display("");
            $display("Expected:");
            $display("   wb_data     = %08h", expected_wb);

            // Print Got
            $display("");
            $display("Got:");
            $display("   wb_data     = %08h", got_wb);

            // Compare
            if (got_wb === expected_wb) begin
                passed_tests = passed_tests + 1;
                $display("STATUS: PASS");
            end
            else begin
                failed_tests = failed_tests + 1;
                $display("STATUS: FAIL");
            end

            print_divider();
            $display("");

            #(TEST_DELAY);
        end
    endtask

    //=============================================================
    // Main Test Sequence
    //=============================================================
    initial begin

        // Init counters
        total_tests  = 0;
        passed_tests = 0;
        failed_tests = 0;

        // Init inputs
        wb_sel      = 3'b000;
        alu_result  = 32'h0000_0000;
        mem_data    = 32'h0000_0000;
        pc_plus4    = 32'h0000_0000;
        u_imm       = 32'h0000_0000;
        pc_plus_imm = 32'h0000_0000;

        $display("====================================================");
        $display(" WB_MUX VERIFICATION STARTED — Author: Prabhat Pandey");
        $display("====================================================");
        $display("");

        // Common test values (easy to track)
        // ALU   = 0xAAAAAAAA
        // MEM   = 0xBBBBBBBB
        // PC+4  = 0x00000044
        // UIMM  = 0x12345000
        // PCIMM = 0x00001000
        //=========================================================

        //=========================================================
        // wb_sel = 000 -> ALU
        //=========================================================
        run_test("wb_sel=000 -> ALU result",
                 3'b000,
                 32'hAAAA_AAAA,
                 32'hBBBB_BBBB,
                 32'h0000_0044,
                 32'h1234_5000,
                 32'h0000_1000,
                 32'hAAAA_AAAA);

        //=========================================================
        // wb_sel = 001 -> MEM
        //=========================================================
        run_test("wb_sel=001 -> Memory data",
                 3'b001,
                 32'hAAAA_AAAA,
                 32'hBBBB_BBBB,
                 32'h0000_0044,
                 32'h1234_5000,
                 32'h0000_1000,
                 32'hBBBB_BBBB);

        //=========================================================
        // wb_sel = 010 -> PC+4
        //=========================================================
        run_test("wb_sel=010 -> PC+4",
                 3'b010,
                 32'hAAAA_AAAA,
                 32'hBBBB_BBBB,
                 32'h0000_0044,
                 32'h1234_5000,
                 32'h0000_1000,
                 32'h0000_0044);

        //=========================================================
        // wb_sel = 011 -> U-IMM (LUI)
        //=========================================================
        run_test("wb_sel=011 -> U-immediate (LUI)",
                 3'b011,
                 32'hAAAA_AAAA,
                 32'hBBBB_BBBB,
                 32'h0000_0044,
                 32'h1234_5000,
                 32'h0000_1000,
                 32'h1234_5000);

        //=========================================================
        // wb_sel = 100 -> PC+IMM (AUIPC)
        //=========================================================
        run_test("wb_sel=100 -> PC+imm (AUIPC)",
                 3'b100,
                 32'hAAAA_AAAA,
                 32'hBBBB_BBBB,
                 32'h0000_0044,
                 32'h1234_5000,
                 32'h0000_1000,
                 32'h0000_1000);

        //=========================================================
        // Invalid wb_sel -> safe 0
        //=========================================================
        run_test("wb_sel invalid -> wb_data must be 0",
                 3'b111,
                 32'hAAAA_AAAA,
                 32'hBBBB_BBBB,
                 32'h0000_0044,
                 32'h1234_5000,
                 32'h0000_1000,
                 32'h0000_0000);

        //=========================================================
        // Final Summary Report
        //=========================================================
        $display("====================================================");
        $display(" WB_MUX VERIFICATION REPORT");
        $display("====================================================");
        $display("   Total Tests   : %0d", total_tests);
        $display("   Passed        : %0d", passed_tests);
        $display("   Failed        : %0d", failed_tests);
        $display("====================================================");

        if (failed_tests == 0) begin
            $display("STATUS: ALL TESTS PASSED");
        end
        else begin
            $display("STATUS: SOME TESTS FAILED");
        end

        $display("====================================================");
        $display("");

        $finish;
    end

endmodule

Verification_Results/vcd/tb_wb_mux.vcd
$date
	Mon Mar  9 20:55:09 2026
$end
$version
	Icarus Verilog
$end
$timescale
	1ps
$end
$scope module tb_wb_mux $end
$var wire 32 ! wb_data [31:0] $end
$var parameter 32 " TEST_DELAY $end
$var reg 32 # alu_result [31:0] $end
$var reg 32 $ mem_data [31:0] $end
$var reg 32 % pc_plus4 [31:0] $end
$var reg 32 & pc_plus_imm [31:0] $end
$var reg 32 ' u_imm [31:0] $end
$var reg 3 ( wb_sel [2:0] $end
$var integer 32 ) failed_tests [31:0] $end
$var integer 32 * passed_tests [31:0] $end
$var integer 32 + total_tests [31:0] $end
$scope module dut $end
$var wire 32 , alu_result [31:0] $end
$var wire 32 - mem_data [31:0] $end
$var wire 32 . pc_plus4 [31:0] $end
$var wire 32 / pc_plus_imm [31:0] $end
$var wire 32 0 u_imm [31:0] $end
$var wire 3 1 wb_sel [2:0] $end
$var reg 32 2 wb_data [31:0] $end
$upscope $end
$scope task print_divider $end
$upscope $end
$scope task run_test $end
$var reg 32 3 alu_in [31:0] $end
$var reg 32 4 expected_wb [31:0] $end
$var reg 32 5 got_wb [31:0] $end
$var reg 32 6 mem_in [31:0] $end
$var reg 32 7 pc4_in [31:0] $end
$var reg 32 8 pcimm_in [31:0] $end
$var reg 560 9 test_name [560:1] $end
$var reg 32 : uimm_in [31:0] $end
$var reg 3 ; wb_sel_in [2:0] $end
$upscope $end
$upscope $end
$enddefinitions $end
$comment Show the parameter values. $end
$dumpall
b1010 "
$end
#0
$dumpvars
b0 ;
b10010001101000101000000000000 :
b11101110110001001011111011100110110010101101100001111010011000000110000001100000010000000101101001111100010000001000001010011000101010100100000011100100110010101110011011101010110110001110100 9
b1000000000000 8
b1000100 7
b10111011101110111011101110111011 6
bx 5
b10101010101010101010101010101010 4
b10101010101010101010101010101010 3
b10101010101010101010101010101010 2
b0 1
b10010001101000101000000000000 0
b1000000000000 /
b1000100 .
b10111011101110111011101110111011 -
b10101010101010101010101010101010 ,
b1 +
b0 *
b0 )
b0 (
b10010001101000101000000000000 '
b1000000000000 &
b1000100 %
b10111011101110111011101110111011 $
b10101010101010101010101010101010 #
b10101010101010101010101010101010 !
$end
#2000
b1 *
b10101010101010101010101010101010 5
#12000
b10111011101110111011101110111011 !
b10111011101110111011101110111011 2
b1 (
b1 1
b10 +
b10111011101110111011101110111011 4
b1 ;
b1110111011000100101111101110011011001010110110000111101001100000011000000110001001000000010110100111110001000000100110101100101011011010110111101110010011110010010000001100100011000010111010001100001 9
#14000
b10 *
b10111011101110111011101110111011 5
#24000
b1000100 !
b1000100 2
b10 (
b10 1
b11 +
b1000100 4
b10 ;
b11101110110001001011111011100110110010101101100001111010011000000110001001100000010000000101101001111100010000001010000010000110010101100110100 9
#26000
b11 *
b1000100 5
#36000
b10010001101000101000000000000 !
b10010001101000101000000000000 2
b11 (
b11 1
b100 +
b10010001101000101000000000000 4
b11 ;
b1110111011000100101111101110011011001010110110000111101001100000011000100110001001000000010110100111110001000000101010100101101011010010110110101101101011001010110010001101001011000010111010001100101001000000010100001001100010101010100100100101001 9
#38000
b100 *
b10010001101000101000000000000 5
#48000
b1000000000000 !
b1000000000000 2
b100 (
b100 1
b101 +
b1000000000000 4
b100 ;
b1110111011000100101111101110011011001010110110000111101001100010011000000110000001000000010110100111110001000000101000001000011001010110110100101101101011011010010000000101000010000010101010101001001010100000100001100101001 9
#50000
b101 *
b1000000000000 5
#60000
b0 !
b0 2
b111 (
b111 1
b110 +
b0 4
b111 ;
b111011101100010010111110111001101100101011011000010000001101001011011100111011001100001011011000110100101100100001000000010110100111110001000000111011101100010010111110110010001100001011101000110000100100000011011010111010101110011011101000010000001100010011001010010000000110000 9
#62000
b110 *
b0 5
